DDCA/Exercises/Chapter_4/Exercise_27/jk_flip_flop.sv
module jk_flip_flop
	(input logic j, k, clk,
	output logic q);

	always_ff @(posedge clk) begin
		case ({j, k})
			2'b00 : q <= q;
			2'b01 : q <= 1'b0;
			2'b10 : q <= 1'b1;
			2'b11 : q <= ~q;
			default : q <= 1'b0;
		endcase
	end
endmodule

DDCA/Exercises/Chapter_4/Exercise_27/tb_jk_flip_flop.sv
module tb_jk_flip_flop();
	localparam vindx = 8;
	logic j, k, clk;
	logic q, q_exp;
	logic[2:0] vector_in[0 : vindx - 1];
	jk_flip_flop dut(.j(j), .k(k), .clk(clk), .q(q));
	initial
	begin
		$readmemb("input_jk_flip_flop.txt", vector_in);
		$dumpfile("waveform_jk_flip_flop.vcd");
		$dumpvars(0, tb_jk_flip_flop);
		clk = 1'b0; #5;
		for (integer i=0; i < vindx; i++)
		begin
			clk = ~clk;
			{j, k, q_exp} = vector_in[i]; #10;
			assert (q === q_exp) else $error("Failed at line %d : input %b output %b", (i+1), {j, k}, q);
		end
	end
endmodule

DDCA/Exercises/Chapter_4/Exercise_27/waveform_jk_flip_flop.vcd
$version Generated by VerilatedVcd $end
$timescale 1ps $end

 $scope module TOP $end
  $scope module tb_jk_flip_flop $end
   $var wire  1 % clk $end
   $var wire  1 # j $end
   $var wire  1 $ k $end
   $var wire  1 0 q $end
   $var wire  1 & q_exp $end
   $var wire  3 ' vector_in[0] [2:0] $end
   $var wire  3 ( vector_in[1] [2:0] $end
   $var wire  3 ) vector_in[2] [2:0] $end
   $var wire  3 * vector_in[3] [2:0] $end
   $var wire  3 + vector_in[4] [2:0] $end
   $var wire  3 , vector_in[5] [2:0] $end
   $var wire  3 - vector_in[6] [2:0] $end
   $var wire  3 . vector_in[7] [2:0] $end
   $var wire 32 1 vindx [31:0] $end
   $scope module dut $end
    $var wire  1 % clk $end
    $var wire  1 # j $end
    $var wire  1 $ k $end
    $var wire  1 0 q $end
   $upscope $end
   $scope module unnamedblk1 $end
    $var wire 32 / i [31:0] $end
   $upscope $end
  $upscope $end
 $upscope $end
$enddefinitions $end


#0
0#
0$
0%
0&
b000 '
b000 (
b010 )
b000 *
b101 +
b001 ,
b110 -
b000 .
b00000000000000000000000000000000 /
00
b00000000000000000000000000001000 1
#5
1%
#15
0%
b00000000000000000000000000000001 /
#25
1$
1%
b00000000000000000000000000000010 /
#35
0$
0%
b00000000000000000000000000000011 /
#45
1#
1%
1&
b00000000000000000000000000000100 /
10
#55
0#
0%
b00000000000000000000000000000101 /
#65
1#
1$
1%
0&
b00000000000000000000000000000110 /
00
#75
0#
0$
0%
b00000000000000000000000000000111 /
#85
b00000000000000000000000000001000 /
