DDCA/Exercises/Chapter_5/Exercise_13/third_alu_32.sv
module third_alu_32
    (input logic[31:0] a,
    input logic[31:0] b,
    input logic[2:0] control,
    output logic[31:0] result);

    logic[31:0] sum;
    logic cout;
    
    always_comb begin
        sum = a+((control[0]==1)?~b:b)+{31'b0, control[0]};
        case (control)
            3'b000 : result = sum;
            3'b001 : result = sum;
            3'b010 : result = a & b;
            3'b011 : result = a | b;
            3'b101 : result = {31'b0, sum[31]};
            default : result = 32'bx;
        endcase
    end
endmodule

DDCA/Exercises/Chapter_5/Exercise_13/tb_third_alu_32.sv
module tb_third_alu_32();
    localparam vindx = 12;
	logic[31:0] a, b;
    logic[2:0] control;
	logic[31:0] result, result_exp;
    logic[98:0] vector_in[0 : vindx - 1];

	third_alu_32 dut(.a(a), .b(b), .control(control), .result(result));

	initial begin
        $readmemh("input_third_alu_32.txt", vector_in);
        $dumpfile("waveform_tb_third_alu_32.vcd");
        $dumpvars(0, tb_third_alu_32);
        for(int i=0; i<vindx; i++) begin
            {control, a, b, result_exp} = vector_in[i]; #10;
            assert 
                (result === result_exp) 
            else 
                $error("Failed at line %d : a=%h, b=%h, control=%b, result=%h", (i+1), a, b, control, result);
        end
        $finish;
	end
endmodule

DDCA/Exercises/Chapter_5/Exercise_13/waveform_tb_third_alu_32.vcd
$version Generated by VerilatedVcd $end
$timescale 1ps $end

 $scope module TOP $end
  $scope module tb_third_alu_32 $end
   $var wire 32 # a [31:0] $end
   $var wire 32 $ b [31:0] $end
   $var wire  3 % control [2:0] $end
   $var wire 32 X result [31:0] $end
   $var wire 32 & result_exp [31:0] $end
   $var wire 99 ' vector_in[0] [98:0] $end
   $var wire 99 O vector_in[10] [98:0] $end
   $var wire 99 S vector_in[11] [98:0] $end
   $var wire 99 + vector_in[1] [98:0] $end
   $var wire 99 / vector_in[2] [98:0] $end
   $var wire 99 3 vector_in[3] [98:0] $end
   $var wire 99 7 vector_in[4] [98:0] $end
   $var wire 99 ; vector_in[5] [98:0] $end
   $var wire 99 ? vector_in[6] [98:0] $end
   $var wire 99 C vector_in[7] [98:0] $end
   $var wire 99 G vector_in[8] [98:0] $end
   $var wire 99 K vector_in[9] [98:0] $end
   $var wire 32 Z vindx [31:0] $end
   $scope module dut $end
    $var wire 32 # a [31:0] $end
    $var wire 32 $ b [31:0] $end
    $var wire  3 % control [2:0] $end
    $var wire  1 [ cout $end
    $var wire 32 X result [31:0] $end
    $var wire 32 Y sum [31:0] $end
   $upscope $end
   $scope module unnamedblk1 $end
    $var wire 32 W i [31:0] $end
   $upscope $end
  $upscope $end
 $upscope $end
$enddefinitions $end


#0
b00000000000000000000000011001000 #
b00000000000000000000000100101100 $
b000 %
b00000000000000000000000111110100 &
b000000000000000000000000000110010000000000000000000000000010010110000000000000000000000000111110100 '
b000111111111111111111111111001110001111111111111111111111101101010011111111111111111111111000001100 +
b000011111111111111111111111111111110111111111111111111111111111111111111111111111111111111111111110 /
b001000000000000000000000000110010000000000000000000000000010010110011111111111111111111111110011100 3
b001111111111111111111111111001110001111111111111111111111101101010000000000000000000000000001100100 7
b001011111111111111111111111111111111000000000000000000000000000000111111111111111111111111111111110 ;
b010110110101000010000010000111000001110011110100001010001101010100011000010100000000000000010100000 ?
b010110110101000010000010000111000000010010101111011111011110001111100000000000000000000000000000000 C
b011110110101000010000010000111000001110011110100001010001101010100011111111101001010101011011101000 G
b011110110101000010000010000111000000010010101111011111011110001111111111111111111111111111111111111 K
b101000000000000000000000000110010000000000000000000000000010010110000000000000000000000000000000001 O
b101111111111111111111111111001110001111111111111111111111101101010000000000000000000000000000000000 S
b00000000000000000000000000000000 W
b00000000000000000000000111110100 X
b00000000000000000000000111110100 Y
b00000000000000000000000000001100 Z
0[
#10
b11111111111111111111111100111000 #
b11111111111111111111111011010100 $
b11111111111111111111111000001100 &
b00000000000000000000000000000001 W
b11111111111111111111111000001100 X
b11111111111111111111111000001100 Y
#20
b01111111111111111111111111111111 #
b01111111111111111111111111111111 $
b11111111111111111111111111111110 &
b00000000000000000000000000000010 W
b11111111111111111111111111111110 X
b11111111111111111111111111111110 Y
#30
b00000000000000000000000011001000 #
b00000000000000000000000100101100 $
b001 %
b11111111111111111111111110011100 &
b00000000000000000000000000000011 W
b11111111111111111111111110011100 X
b11111111111111111111111110011100 Y
#40
b11111111111111111111111100111000 #
b11111111111111111111111011010100 $
b00000000000000000000000001100100 &
b00000000000000000000000000000100 W
b00000000000000000000000001100100 X
b00000000000000000000000001100100 Y
#50
b01111111111111111111111111111111 #
b10000000000000000000000000000001 $
b11111111111111111111111111111110 &
b00000000000000000000000000000101 W
b11111111111111111111111111111110 X
b11111111111111111111111111111110 Y
#60
b11011010100001000001000011100000 #
b11100111101000010100011010101000 $
b010 %
b11000010100000000000000010100000 &
b00000000000000000000000000000110 W
b11000010100000000000000010100000 X
b11000010001001010101011110001000 Y
#70
b00100101011110111110111100011111 $
b00000000000000000000000000000000 &
b00000000000000000000000000000111 W
b00000000000000000000000000000000 X
b11111111111111111111111111111111 Y
#80
b11100111101000010100011010101000 $
b011 %
b11111111101001010101011011101000 &
b00000000000000000000000000001000 W
b11111111101001010101011011101000 X
b11110010111000101100101000111000 Y
#90
b00100101011110111110111100011111 $
b11111111111111111111111111111111 &
b00000000000000000000000000001001 W
b11111111111111111111111111111111 X
b10110101000010000010000111000001 Y
#100
b00000000000000000000000011001000 #
b00000000000000000000000100101100 $
b101 %
b00000000000000000000000000000001 &
b00000000000000000000000000001010 W
b00000000000000000000000000000001 X
b11111111111111111111111110011100 Y
#110
b11111111111111111111111100111000 #
b11111111111111111111111011010100 $
b00000000000000000000000000000000 &
b00000000000000000000000000001011 W
b00000000000000000000000000000000 X
b00000000000000000000000001100100 Y
#120
b00000000000000000000000000001100 W
