DDCA/Exercises/Chapter_4/Exercise_09/mux8.sv
module mux8
    (input logic[2:0] sel,
    input logic d7, d6, d5, d4, d3, d2, d1, d0,
    output logic y);

    always_comb begin
        case(sel)
            3'b111: y = d7;
            3'b110: y = d6;
            3'b101: y = d5;
            3'b100: y = d4;
            3'b011: y = d3;
            3'b010: y = d2;
            3'b001: y = d1;
            3'b000: y = d0;
            default: y = 1'bx;
        endcase
    end
endmodule

DDCA/Exercises/Chapter_4/Exercise_09/logic_mux8.sv
module logic_mux8
    (input logic a, b, c,
    output logic y);

    logic d7, d6, d5, d4, d3, d2, d1, d0;
    logic[2:0] sel;

    mux8 mux(.sel(sel), .d7(d7), .d6(d6), .d5(d5), .d4(d4), .d3(d3), .d2(d2), .d1(d1), .d0(d0), .y(y));

    always_comb begin
        sel = {a ,b ,c};
        {d7, d6, d5, d4, d3, d2, d1, d0} = 8'b00111001;
    end
endmodule

DDCA/Exercises/Chapter_4/Exercise_09/tb_logic_mux8.sv
module tb_logic_mux8();
    localparam vindx = 8;
    logic a, b, c;
    logic y, y_exp;
    logic[3:0] vector_in[0 : vindx - 1];
    logic_mux8 dut(.a(a), .b(b), .c(c), .y(y));
    initial
    begin
        $readmemb("input_logic_mux8.txt", vector_in);
        $dumpfile("waveform_logic_mux8.vcd");
        $dumpvars(0, tb_logic_mux8);
        for (integer i=0; i < vindx; i++)
        begin
            {a, b, c, y_exp} = vector_in[i]; #10;
            assert (y === y_exp) else $error("Failed at line %d : input %b output %b", (i+1), {a, b, c}, y);
        end
    end
endmodule

DDCA/Exercises/Chapter_4/Exercise_09/waveform_logic_mux8.vcd
$version Generated by VerilatedVcd $end
$timescale 1ps $end

 $scope module TOP $end
  $scope module tb_logic_mux8 $end
   $var wire  1 # a $end
   $var wire  1 $ b $end
   $var wire  1 % c $end
   $var wire  4 ' vector_in[0] [3:0] $end
   $var wire  4 ( vector_in[1] [3:0] $end
   $var wire  4 ) vector_in[2] [3:0] $end
   $var wire  4 * vector_in[3] [3:0] $end
   $var wire  4 + vector_in[4] [3:0] $end
   $var wire  4 , vector_in[5] [3:0] $end
   $var wire  4 - vector_in[6] [3:0] $end
   $var wire  4 . vector_in[7] [3:0] $end
   $var wire 32 2 vindx [31:0] $end
   $var wire  1 1 y $end
   $var wire  1 & y_exp $end
   $scope module dut $end
    $var wire  1 # a $end
    $var wire  1 $ b $end
    $var wire  1 % c $end
    $var wire  1 4 d0 $end
    $var wire  1 3 d1 $end
    $var wire  1 3 d2 $end
    $var wire  1 4 d3 $end
    $var wire  1 4 d4 $end
    $var wire  1 4 d5 $end
    $var wire  1 3 d6 $end
    $var wire  1 3 d7 $end
    $var wire  3 / sel [2:0] $end
    $var wire  1 1 y $end
    $scope module mux $end
     $var wire  1 4 d0 $end
     $var wire  1 3 d1 $end
     $var wire  1 3 d2 $end
     $var wire  1 4 d3 $end
     $var wire  1 4 d4 $end
     $var wire  1 4 d5 $end
     $var wire  1 3 d6 $end
     $var wire  1 3 d7 $end
     $var wire  3 / sel [2:0] $end
     $var wire  1 1 y $end
    $upscope $end
   $upscope $end
   $scope module unnamedblk1 $end
    $var wire 32 0 i [31:0] $end
   $upscope $end
  $upscope $end
 $upscope $end
$enddefinitions $end


#0
1#
1$
1%
0&
b1110 '
b1100 (
b1011 )
b1001 *
b0111 +
b0100 ,
b0010 -
b0001 .
b111 /
b00000000000000000000000000000000 0
01
b00000000000000000000000000001000 2
03
14
#10
0%
b110 /
b00000000000000000000000000000001 0
#20
0$
1%
1&
b101 /
b00000000000000000000000000000010 0
11
#30
0%
b100 /
b00000000000000000000000000000011 0
#40
0#
1$
1%
b011 /
b00000000000000000000000000000100 0
#50
0%
0&
b010 /
b00000000000000000000000000000101 0
01
#60
0$
1%
b001 /
b00000000000000000000000000000110 0
#70
0%
1&
b000 /
b00000000000000000000000000000111 0
11
#80
b00000000000000000000000000001000 0
