DDCA/Exercises/Chapter_4/Exercise_38/gray_code_up.sv
module gray_code_up
	(input logic up,
	input logic clk, reset,
	output logic[2:0] y);

	logic[2:0] state, nextstate;

	parameter S0 = 3'b000;
	parameter S1 = 3'b001;
	parameter S2 = 3'b011;
	parameter S3 = 3'b010;
	parameter S4 = 3'b110;
	parameter S5 = 3'b111;
	parameter S6 = 3'b101;
	parameter S7 = 3'b100;

	always_ff @(posedge clk, posedge reset) begin
		if (reset)
			state <= S0;
		else
			state <= nextstate;
	end

	always_comb begin
		case (state)
			S0 : if (up) nextstate = S1;
				else nextstate = S7;
			S1 : if (up) nextstate = S2;
				else nextstate = S0;
			S2 : if (up) nextstate = S3;
				else nextstate = S1;
			S3 : if (up) nextstate = S4;
				else nextstate = S2;
			S4 : if (up) nextstate = S5;
				else nextstate = S3;
			S5 : if (up) nextstate = S6;
				else nextstate = S4;
			S6 : if (up) nextstate = S7;
				else nextstate = S5;
			S7 : if (up) nextstate = S0;
				else nextstate = S6;
		endcase
	end

	assign y = state;
endmodule

DDCA/Exercises/Chapter_4/Exercise_38/tb_gray_code_up.sv
module tb_gray_code_up();
	integer vindx;
    localparam top=16;
	logic up;
	logic clk, reset;
	logic[2:0] y, y_exp;
	logic[3:0] vector_in[0 : 100];
	gray_code_up dut(.up(up), .clk(clk), .reset(reset), .y(y));

	initial begin
		$readmemb("input_gray_code_up.txt", vector_in);
		$dumpfile("waveform_gray_code_up.vcd");
		$dumpvars(0, tb_gray_code_up);
		vindx = 0;
		reset = 1; #15; reset = 0;
	end

	always begin
		clk = 0; #10;
		clk = 1; #10;
	end

	always @(posedge clk) begin
		{up, y_exp} = vector_in[vindx];
	end

	always @(negedge clk) begin
		if (~reset) begin
 			if (y !== y_exp) begin
				$display("Failed at line %d : input %b output %b", (vindx+1), up, y);
			end
			vindx++;
			if (vindx>=top) begin
				$display("Test finished");
				$finish;
			end
		end
	end
endmodule

DDCA/Exercises/Chapter_4/Exercise_38/waveform_gray_code_up.vcd
$version Generated by VerilatedVcd $end
$timescale 1ps $end

 $scope module TOP $end
  $scope module tb_gray_code_up $end
   $var wire  1 % clk $end
   $var wire  1 & reset $end
   $var wire 32 * top [31:0] $end
   $var wire  1 $ up $end
   $var wire 32 # vindx [31:0] $end
   $var wire  3 ' y [2:0] $end
   $var wire  3 ( y_exp [2:0] $end
   $scope module dut $end
    $var wire  3 + S0 [2:0] $end
    $var wire  3 , S1 [2:0] $end
    $var wire  3 - S2 [2:0] $end
    $var wire  3 . S3 [2:0] $end
    $var wire  3 / S4 [2:0] $end
    $var wire  3 0 S5 [2:0] $end
    $var wire  3 1 S6 [2:0] $end
    $var wire  3 2 S7 [2:0] $end
    $var wire  1 % clk $end
    $var wire  3 ) nextstate [2:0] $end
    $var wire  1 & reset $end
    $var wire  3 ' state [2:0] $end
    $var wire  1 $ up $end
    $var wire  3 ' y [2:0] $end
   $upscope $end
  $upscope $end
 $upscope $end
$enddefinitions $end


#0
b00000000000000000000000000000000 #
0$
0%
1&
b000 '
b000 (
b100 )
b00000000000000000000000000010000 *
b000 +
b001 ,
b011 -
b010 .
b110 /
b111 0
b101 1
b100 2
#10
1%
#15
0&
#20
b00000000000000000000000000000001 #
0%
#30
1%
b100 '
b100 (
b101 )
#40
b00000000000000000000000000000010 #
0%
#50
1%
b101 '
b101 (
b111 )
#60
b00000000000000000000000000000011 #
0%
#70
1%
b111 '
b111 (
b110 )
#80
b00000000000000000000000000000100 #
0%
#90
1%
b110 '
b110 (
b010 )
#100
b00000000000000000000000000000101 #
0%
#110
1%
b010 '
b010 (
b011 )
#120
b00000000000000000000000000000110 #
0%
#130
1%
b011 '
b011 (
b001 )
#140
b00000000000000000000000000000111 #
0%
#150
1%
b001 '
b001 (
b000 )
#160
b00000000000000000000000000001000 #
0%
#170
1$
1%
b000 '
b000 (
b001 )
#180
b00000000000000000000000000001001 #
0%
#190
1%
b001 '
b001 (
b011 )
#200
b00000000000000000000000000001010 #
0%
#210
1%
b011 '
b011 (
b010 )
#220
b00000000000000000000000000001011 #
0%
#230
1%
b010 '
b010 (
b110 )
#240
b00000000000000000000000000001100 #
0%
#250
1%
b110 '
b110 (
b111 )
#260
b00000000000000000000000000001101 #
0%
#270
1%
b111 '
b111 (
b101 )
#280
b00000000000000000000000000001110 #
0%
#290
1%
b101 '
b101 (
b100 )
#300
b00000000000000000000000000001111 #
0%
#310
1%
b100 '
b100 (
b000 )
#320
b00000000000000000000000000010000 #
0%
