DDCA/Exercises/Chapter_4/Exercise_18/dont_care.sv
module dont_care 
	(input logic a, b, c, d,
	output logic y);

	always_comb begin
		case ({a, b, c, d})
			4'b0000 : y = 1'bx;
			4'b0001 : y = 1'bx;
			4'b0010 : y = 1'bx;
			4'b0011 : y = 1'b0;
			4'b0100 : y = 1'b0;
			4'b0101 : y = 1'bx;
			4'b0110 : y = 1'b0;
			4'b0111 : y = 1'bx;
			4'b1000 : y = 1'b1;
			4'b1001 : y = 1'b0;
			4'b1010 : y = 1'bx;
			4'b1011 : y = 1'b1;
			4'b1100 : y = 1'b1;
			4'b1101 : y = 1'b1;
			4'b1110 : y = 1'bx;
			4'b1111 : y = 1'b1;
		endcase
	end
endmodule

DDCA/Exercises/Chapter_4/Exercise_18/tb_dont_care.sv
module tb_dont_care();
	localparam vindx = 16;
	logic a, b, c, d;
	logic y, y_exp;
	logic[4:0] vector_in[0 : vindx - 1];
	dont_care dut(.a(a), .b(b), .c(c), .d(d), .y(y));
	initial
	begin
		$readmemb("input_dont_care.txt", vector_in);
		$dumpfile("waveform_dont_care.vcd");
		$dumpvars(0, tb_dont_care);
		for (integer i=0; i < vindx; i++)
		begin
			{a, b, c, d, y_exp} = vector_in[i]; #10;
			assert (y === y_exp) else $error("Failed at line %d : input %b output %b", (i+1), {a, b, c, d}, y);
		end
	end
endmodule

DDCA/Exercises/Chapter_4/Exercise_18/waveform_dont_care.vcd
$version Generated by VerilatedVcd $end
$timescale 1ps $end

 $scope module TOP $end
  $scope module tb_dont_care $end
   $var wire  1 # a $end
   $var wire  1 $ b $end
   $var wire  1 % c $end
   $var wire  1 & d $end
   $var wire  5 ) vector_in[0] [4:0] $end
   $var wire  5 3 vector_in[10] [4:0] $end
   $var wire  5 4 vector_in[11] [4:0] $end
   $var wire  5 5 vector_in[12] [4:0] $end
   $var wire  5 6 vector_in[13] [4:0] $end
   $var wire  5 7 vector_in[14] [4:0] $end
   $var wire  5 8 vector_in[15] [4:0] $end
   $var wire  5 * vector_in[1] [4:0] $end
   $var wire  5 + vector_in[2] [4:0] $end
   $var wire  5 , vector_in[3] [4:0] $end
   $var wire  5 - vector_in[4] [4:0] $end
   $var wire  5 . vector_in[5] [4:0] $end
   $var wire  5 / vector_in[6] [4:0] $end
   $var wire  5 0 vector_in[7] [4:0] $end
   $var wire  5 1 vector_in[8] [4:0] $end
   $var wire  5 2 vector_in[9] [4:0] $end
   $var wire 32 : vindx [31:0] $end
   $var wire  1 ' y $end
   $var wire  1 ( y_exp $end
   $scope module dut $end
    $var wire  1 # a $end
    $var wire  1 $ b $end
    $var wire  1 % c $end
    $var wire  1 & d $end
    $var wire  1 ' y $end
   $upscope $end
   $scope module unnamedblk1 $end
    $var wire 32 9 i [31:0] $end
   $upscope $end
  $upscope $end
 $upscope $end
$enddefinitions $end


#0
0#
0$
0%
0&
0'
0(
b00000 )
b00010 *
b00100 +
b00110 ,
b01000 -
b01010 .
b01100 /
b01110 0
b10001 1
b10010 2
b10100 3
b10111 4
b11001 5
b11011 6
b11100 7
b11111 8
b00000000000000000000000000000000 9
b00000000000000000000000000010000 :
#10
1&
b00000000000000000000000000000001 9
#20
1%
0&
b00000000000000000000000000000010 9
#30
1&
b00000000000000000000000000000011 9
#40
1$
0%
0&
b00000000000000000000000000000100 9
#50
1&
b00000000000000000000000000000101 9
#60
1%
0&
b00000000000000000000000000000110 9
#70
1&
b00000000000000000000000000000111 9
#80
1#
0$
0%
0&
1'
1(
b00000000000000000000000000001000 9
#90
1&
0'
0(
b00000000000000000000000000001001 9
#100
1%
0&
b00000000000000000000000000001010 9
#110
1&
1'
1(
b00000000000000000000000000001011 9
#120
1$
0%
0&
b00000000000000000000000000001100 9
#130
1&
b00000000000000000000000000001101 9
#140
1%
0&
0'
0(
b00000000000000000000000000001110 9
#150
1&
1'
1(
b00000000000000000000000000001111 9
#160
b00000000000000000000000000010000 9
