DDCA/Exercises/Chapter_4/Exercise_03/xor4.sv
module xor4 
    (input logic[3:0] a,
    output logic y);

    always_comb begin
        y = ^a;
    end
endmodule

DDCA/Exercises/Chapter_4/Exercise_03/tb_xor4.sv
module tb_xor4();
    localparam vindx = 16;
    logic[3:0] a;
    logic y, y_exp;
    logic[4:0] vector_in[0 : vindx - 1];
    xor4 dut(.a(a), .y(y));
    initial
    begin
        $readmemb("input_xor4.txt", vector_in);
        $dumpfile("waveform_xor4.vcd");
        $dumpvars(0, tb_xor4);
        for (integer i=0; i < vindx; i++)
        begin
            {a, y_exp} = vector_in[i]; #10;
            assert (y === y_exp) else $error("Failed at line %d: input %b output %b", (i+1), a, y);
        end
    end
endmodule

DDCA/Exercises/Chapter_4/Exercise_03/waveform_xor4.vcd
$version Generated by VerilatedVcd $end
$timescale 1ps $end

 $scope module TOP $end
  $scope module tb_xor4 $end
   $var wire  4 # a [3:0] $end
   $var wire  5 & vector_in[0] [4:0] $end
   $var wire  5 0 vector_in[10] [4:0] $end
   $var wire  5 1 vector_in[11] [4:0] $end
   $var wire  5 2 vector_in[12] [4:0] $end
   $var wire  5 3 vector_in[13] [4:0] $end
   $var wire  5 4 vector_in[14] [4:0] $end
   $var wire  5 5 vector_in[15] [4:0] $end
   $var wire  5 ' vector_in[1] [4:0] $end
   $var wire  5 ( vector_in[2] [4:0] $end
   $var wire  5 ) vector_in[3] [4:0] $end
   $var wire  5 * vector_in[4] [4:0] $end
   $var wire  5 + vector_in[5] [4:0] $end
   $var wire  5 , vector_in[6] [4:0] $end
   $var wire  5 - vector_in[7] [4:0] $end
   $var wire  5 . vector_in[8] [4:0] $end
   $var wire  5 / vector_in[9] [4:0] $end
   $var wire 32 7 vindx [31:0] $end
   $var wire  1 $ y $end
   $var wire  1 % y_exp $end
   $scope module dut $end
    $var wire  4 # a [3:0] $end
    $var wire  1 $ y $end
   $upscope $end
   $scope module unnamedblk1 $end
    $var wire 32 6 i [31:0] $end
   $upscope $end
  $upscope $end
 $upscope $end
$enddefinitions $end


#0
b0000 #
0$
0%
b00000 &
b00011 '
b00101 (
b00110 )
b01001 *
b01010 +
b01100 ,
b01111 -
b10001 .
b10010 /
b10100 0
b10111 1
b11000 2
b11011 3
b11101 4
b00000 5
b00000000000000000000000000000000 6
b00000000000000000000000000010000 7
#10
b0001 #
1$
1%
b00000000000000000000000000000001 6
#20
b0010 #
b00000000000000000000000000000010 6
#30
b0011 #
0$
0%
b00000000000000000000000000000011 6
#40
b0100 #
1$
1%
b00000000000000000000000000000100 6
#50
b0101 #
0$
0%
b00000000000000000000000000000101 6
#60
b0110 #
b00000000000000000000000000000110 6
#70
b0111 #
1$
1%
b00000000000000000000000000000111 6
#80
b1000 #
b00000000000000000000000000001000 6
#90
b1001 #
0$
0%
b00000000000000000000000000001001 6
#100
b1010 #
b00000000000000000000000000001010 6
#110
b1011 #
1$
1%
b00000000000000000000000000001011 6
#120
b1100 #
0$
0%
b00000000000000000000000000001100 6
#130
b1101 #
1$
1%
b00000000000000000000000000001101 6
#140
b1110 #
b00000000000000000000000000001110 6
#150
b0000 #
0$
0%
b00000000000000000000000000001111 6
#160
b00000000000000000000000000010000 6
