DDCA/Exercises/Chapter_4/Exercise_26/sr_latch.sv
module sr_latch 
	(input logic s, r,
	output logic q, nq);

	assign nq = s ~| q;
	assign q = r ~| nq;
endmodule

DDCA/Exercises/Chapter_4/Exercise_26/tb_sr_latch.sv
module tb_sr_latch();
	localparam vindx = 7;
	logic s, r;
	logic q, q_exp, nq, nq_exp;
	logic[3:0] vector_in[0 : vindx - 1];
	sr_latch dut(.s(s), .r(r), .q(q), .nq(nq));
	initial
	begin
		$readmemb("input_sr_latch.txt", vector_in);
		$dumpfile("waveform_sr_latch.vcd");
		$dumpvars(0, tb_sr_latch);
		for (integer i=0; i < vindx; i++)
		begin
			{s, r, q_exp, nq_exp} = vector_in[i]; #10;
			assert (q === q_exp && nq === nq_exp) else $error("Failed at line %d : input %b output %b", (i+1), {s, r}, {q, nq});
		end
	end
endmodule

DDCA/Exercises/Chapter_4/Exercise_26/waveform_sr_latch.vcd
$version Generated by VerilatedVcd $end
$timescale 1ps $end

 $scope module TOP $end
  $scope module tb_sr_latch $end
   $var wire  1 0 nq $end
   $var wire  1 & nq_exp $end
   $var wire  1 / q $end
   $var wire  1 % q_exp $end
   $var wire  1 $ r $end
   $var wire  1 # s $end
   $var wire  4 ' vector_in[0] [3:0] $end
   $var wire  4 ( vector_in[1] [3:0] $end
   $var wire  4 ) vector_in[2] [3:0] $end
   $var wire  4 * vector_in[3] [3:0] $end
   $var wire  4 + vector_in[4] [3:0] $end
   $var wire  4 , vector_in[5] [3:0] $end
   $var wire  4 - vector_in[6] [3:0] $end
   $var wire 32 1 vindx [31:0] $end
   $scope module dut $end
    $var wire  1 0 nq $end
    $var wire  1 / q $end
    $var wire  1 $ r $end
    $var wire  1 # s $end
   $upscope $end
   $scope module unnamedblk1 $end
    $var wire 32 . i [31:0] $end
   $upscope $end
  $upscope $end
 $upscope $end
$enddefinitions $end


#0
0#
0$
0%
1&
b0001 '
b1010 (
b0010 )
b0101 *
b0001 +
b1100 ,
b0001 -
b00000000000000000000000000000000 .
0/
10
b00000000000000000000000000000111 1
#10
1#
1%
0&
b00000000000000000000000000000001 .
1/
00
#20
0#
b00000000000000000000000000000010 .
#30
1$
0%
1&
b00000000000000000000000000000011 .
0/
10
#40
0$
b00000000000000000000000000000100 .
#50
1#
1$
0&
b00000000000000000000000000000101 .
00
#60
0#
0$
1&
b00000000000000000000000000000110 .
10
#70
b00000000000000000000000000000111 .
