DDCA/Exercises/Chapter_5/Exercise_22/rr_shifter/rr_shifter.sv
module rr_shifter
    (input logic[3:0] a,
    input logic[1:0] shamt,
    output logic[3:0] y);
    
    always_comb begin
        case (shamt)
            2'b00 : y = {a[3], a[2], a[1], a[0]};
            2'b01 : y = {a[0], a[3], a[2], a[1]};
            2'b10 : y = {a[1], a[0], a[3], a[2]};
            2'b11 : y = {a[2], a[1], a[0], a[3]};
            default : y = 4'bx;
        endcase
    end
endmodule

DDCA/Exercises/Chapter_5/Exercise_22/rr_shifter/tb_rr_shift.sv
module tb_rr_shifter();
    localparam vindx = 12;
	logic[3:0] a;
    logic[1:0] shamt;
	logic[3:0] y, y_exp;
    logic[9:0] vector_in[0 : vindx - 1];

    rr_shifter dut(.a(a), .shamt(shamt), .y(y));

	initial begin
        $readmemb("input_rr_shift.txt", vector_in);
        $dumpfile("waveform_tb_rr_shift.vcd");
        $dumpvars(0, tb_rr_shifter);
        for(int i=0; i<vindx; i++) begin
            {a, shamt, y_exp} = vector_in[i]; #10;
            assert 
                (y === y_exp) 
            else 
                $error("Failed at line %d : a=%b, shamt=%b, y=%b", (i+1), a, shamt, y);
        end
        $finish;
	end
endmodule

DDCA/Exercises/Chapter_5/Exercise_22/rr_shifter/waveform_tb_rr_shift.vcd
$version Generated by VerilatedVcd $end
$timescale 1ps $end

 $scope module TOP $end
  $scope module tb_rr_shifter $end
   $var wire  4 # a [3:0] $end
   $var wire  2 $ shamt [1:0] $end
   $var wire 10 & vector_in[0] [9:0] $end
   $var wire 10 0 vector_in[10] [9:0] $end
   $var wire 10 1 vector_in[11] [9:0] $end
   $var wire 10 ' vector_in[1] [9:0] $end
   $var wire 10 ( vector_in[2] [9:0] $end
   $var wire 10 ) vector_in[3] [9:0] $end
   $var wire 10 * vector_in[4] [9:0] $end
   $var wire 10 + vector_in[5] [9:0] $end
   $var wire 10 , vector_in[6] [9:0] $end
   $var wire 10 - vector_in[7] [9:0] $end
   $var wire 10 . vector_in[8] [9:0] $end
   $var wire 10 / vector_in[9] [9:0] $end
   $var wire 32 4 vindx [31:0] $end
   $var wire  4 3 y [3:0] $end
   $var wire  4 % y_exp [3:0] $end
   $scope module dut $end
    $var wire  4 # a [3:0] $end
    $var wire  2 $ shamt [1:0] $end
    $var wire  4 3 y [3:0] $end
   $upscope $end
   $scope module unnamedblk1 $end
    $var wire 32 2 i [31:0] $end
   $upscope $end
  $upscope $end
 $upscope $end
$enddefinitions $end


#0
b0001 #
b00 $
b0001 %
b0001000001 &
b0001011000 '
b0001100100 (
b0001110010 )
b1011001011 *
b1011011101 +
b1011101110 ,
b1011110111 -
b0110000110 .
b0110010011 /
b0110101001 0
b0110111100 1
b00000000000000000000000000000000 2
b0001 3
b00000000000000000000000000001100 4
#10
b01 $
b1000 %
b00000000000000000000000000000001 2
b1000 3
#20
b10 $
b0100 %
b00000000000000000000000000000010 2
b0100 3
#30
b11 $
b0010 %
b00000000000000000000000000000011 2
b0010 3
#40
b1011 #
b00 $
b1011 %
b00000000000000000000000000000100 2
b1011 3
#50
b01 $
b1101 %
b00000000000000000000000000000101 2
b1101 3
#60
b10 $
b1110 %
b00000000000000000000000000000110 2
b1110 3
#70
b11 $
b0111 %
b00000000000000000000000000000111 2
b0111 3
#80
b0110 #
b00 $
b0110 %
b00000000000000000000000000001000 2
b0110 3
#90
b01 $
b0011 %
b00000000000000000000000000001001 2
b0011 3
#100
b10 $
b1001 %
b00000000000000000000000000001010 2
b1001 3
#110
b11 $
b1100 %
b00000000000000000000000000001011 2
b1100 3
#120
b00000000000000000000000000001100 2
