DDCA/Exercises/Chapter_4/Exercise_31/timming.sv
module timming 
	(input logic a, b, c, d,
	input logic clk,
	output logic x, y);

	logic a_reg, b_reg, c_reg, d_reg;
	logic n1, n2, n3;

	always_ff @(posedge(clk)) begin
		{a_reg, b_reg, c_reg, d_reg} <= {a, b, c, d};
		{x, y} <= {n2, n3};
	end

	assign n1 = (a_reg & b_reg); 
	assign n2 = (n1 | c_reg);
	assign n3 = ~(n2 | d_reg);
endmodule

DDCA/Exercises/Chapter_4/Exercise_31/tb_timming.sv
module tb_timming();
	integer vindx;
    localparam top=17;
	logic a, b, c, d;
	logic clk;
	logic x, x_exp, y, y_exp;
	logic[5:0] vector_in[0 : top-1];
	timming dut(.a(a), .b(b), .c(c), .d(d), .clk(clk), .x(x), .y(y));

	initial begin
		$readmemb("input_timming.txt", vector_in);
		$dumpfile("waveform_timming.vcd");
		$dumpvars(0, tb_timming);
		vindx = 0;
	end

	always begin
		clk = 0; #10;
		clk = 1; #10;
	end

	always @(posedge clk) begin
		{a, b, c, d, x_exp, y_exp} = vector_in[vindx]; #15;
	end

	always @(negedge clk) begin
		if (x !== x_exp || y !== y_exp) begin
			$display("Failed at line %d : input %b output %b", (vindx+1), {a, b, c, d}, {x, y});
		end
		vindx++;
		if (vindx>=top) begin
			$display("Test finished");
			$finish;
		end
	end
endmodule

DDCA/Exercises/Chapter_4/Exercise_31/waveform_timming.vcd
$version Generated by VerilatedVcd $end
$timescale 1ps $end

 $scope module TOP $end
  $scope module tb_timming $end
   $var wire  1 4 a $end
   $var wire  1 5 b $end
   $var wire  1 6 c $end
   $var wire  1 D clk $end
   $var wire  1 7 d $end
   $var wire 32 E top [31:0] $end
   $var wire  6 # vector_in[0] [5:0] $end
   $var wire  6 - vector_in[10] [5:0] $end
   $var wire  6 . vector_in[11] [5:0] $end
   $var wire  6 / vector_in[12] [5:0] $end
   $var wire  6 0 vector_in[13] [5:0] $end
   $var wire  6 1 vector_in[14] [5:0] $end
   $var wire  6 2 vector_in[15] [5:0] $end
   $var wire  6 3 vector_in[16] [5:0] $end
   $var wire  6 $ vector_in[1] [5:0] $end
   $var wire  6 % vector_in[2] [5:0] $end
   $var wire  6 & vector_in[3] [5:0] $end
   $var wire  6 ' vector_in[4] [5:0] $end
   $var wire  6 ( vector_in[5] [5:0] $end
   $var wire  6 ) vector_in[6] [5:0] $end
   $var wire  6 * vector_in[7] [5:0] $end
   $var wire  6 + vector_in[8] [5:0] $end
   $var wire  6 , vector_in[9] [5:0] $end
   $var wire 32 C vindx [31:0] $end
   $var wire  1 : x $end
   $var wire  1 8 x_exp $end
   $var wire  1 ; y $end
   $var wire  1 9 y_exp $end
   $scope module dut $end
    $var wire  1 4 a $end
    $var wire  1 < a_reg $end
    $var wire  1 5 b $end
    $var wire  1 = b_reg $end
    $var wire  1 6 c $end
    $var wire  1 > c_reg $end
    $var wire  1 D clk $end
    $var wire  1 7 d $end
    $var wire  1 ? d_reg $end
    $var wire  1 @ n1 $end
    $var wire  1 A n2 $end
    $var wire  1 B n3 $end
    $var wire  1 : x $end
    $var wire  1 ; y $end
   $upscope $end
  $upscope $end
 $upscope $end
$enddefinitions $end


#0
b000001 #
b000101 $
b001000 %
b001110 &
b010010 '
b010101 (
b011000 )
b011110 *
b100010 +
b100101 ,
b101000 -
b101110 .
b110010 /
b110110 0
b111010 1
b111110 2
b000010 3
04
05
06
07
08
09
0:
0;
0<
0=
0>
0?
0@
0A
1B
b00000000000000000000000000000000 C
0D
b00000000000000000000000000010001 E
#10
19
1;
1D
#20
b00000000000000000000000000000001 C
0D
#25
#30
17
1?
0B
1D
#40
b00000000000000000000000000000010 C
0D
#45
#50
16
07
09
0;
1>
0?
1A
1D
#60
b00000000000000000000000000000011 C
0D
#65
#70
17
18
1:
1?
1D
#80
b00000000000000000000000000000100 C
0D
#85
#90
15
06
07
1=
0>
0?
0A
1B
1D
#100
b00000000000000000000000000000101 C
0D
#105
#110
17
08
19
0:
1;
1?
0B
1D
#120
b00000000000000000000000000000110 C
0D
#125
#130
16
07
09
0;
1>
0?
1A
1D
#140
b00000000000000000000000000000111 C
0D
#145
#150
17
18
1:
1?
1D
#160
b00000000000000000000000000001000 C
0D
#165
#170
14
05
06
07
1<
0=
0>
0?
0A
1B
1D
#180
b00000000000000000000000000001001 C
0D
#185
#190
17
08
19
0:
1;
1?
0B
1D
#200
b00000000000000000000000000001010 C
0D
#205
#210
16
07
09
0;
1>
0?
1A
1D
#220
b00000000000000000000000000001011 C
0D
#225
#230
17
18
1:
1?
1D
#240
b00000000000000000000000000001100 C
0D
#245
#250
15
06
07
1=
0>
0?
1@
1D
#260
b00000000000000000000000000001101 C
0D
#265
#270
17
1?
1D
#280
b00000000000000000000000000001110 C
0D
#285
#290
16
07
1>
0?
1D
#300
b00000000000000000000000000001111 C
0D
#305
#310
17
1?
1D
#320
b00000000000000000000000000010000 C
0D
#325
#330
04
05
06
07
0<
0=
0>
0?
0@
0A
1B
1D
#340
b00000000000000000000000000010001 C
0D
