DDCA/Exercises/Chapter_4/Exercise_15/bool_eq.sv
module bool_eq
	(input logic a, b, c, d,
	output logic y2, y1, y0);

	always_comb begin
		y2 = (a & c) | (~a & ~b & c);
		y1 = (~a & ~b) | (~a & b & ~c) | ~(a | ~c);
		y0 = (~a & ~b & ~c & ~d) | (a & ~b & ~c) | (a & ~b & c & ~d) | (a & b & d) |(~a & ~b & c & ~d) | (b & ~c & d) | ~a;
	end
endmodule

DDCA/Exercises/Chapter_4/Exercise_15/tb_bool_eq.sv
module tb_bool_eq();
	localparam vindx = 16;
	logic a, b, c, d;
	logic y2, y1, y0, y2_exp, y1_exp, y0_exp;
	logic[6:0] vector_in[0 : vindx - 1];
	bool_eq dut(.a(a), .b(b), .c(c), .d(d), .y2(y2), .y1(y1), .y0(y0));
	initial
	begin
		$readmemb("input_bool_eq.txt", vector_in);
		$dumpfile("waveform_bool_eq.vcd");
		$dumpvars(0, tb_bool_eq);
		for (integer i=0; i < vindx; i++)
		begin
			{a, b, c, d, y2_exp, y1_exp, y0_exp} = vector_in[i]; #10;
			assert (y2 === y2_exp) else $error("Failed at line %d : input %b output y2 = %b", (i+1), {a, b, c, d}, y2);
			assert (y1 === y1_exp) else $error("Failed at line %d : input %b output y1 = %b", (i+1), {a, b, c, d}, y1);
			assert (y0 === y0_exp) else $error("Failed at line %d : input %b output y0 = %b", (i+1), {a, b, c, d}, y0);
		end
	end
endmodule

DDCA/Exercises/Chapter_4/Exercise_15/waveform_bool_eq.vcd
$version Generated by VerilatedVcd $end
$timescale 1ps $end

 $scope module TOP $end
  $scope module tb_bool_eq $end
   $var wire  1 # a $end
   $var wire  1 $ b $end
   $var wire  1 % c $end
   $var wire  1 & d $end
   $var wire  7 * vector_in[0] [6:0] $end
   $var wire  7 4 vector_in[10] [6:0] $end
   $var wire  7 5 vector_in[11] [6:0] $end
   $var wire  7 6 vector_in[12] [6:0] $end
   $var wire  7 7 vector_in[13] [6:0] $end
   $var wire  7 8 vector_in[14] [6:0] $end
   $var wire  7 9 vector_in[15] [6:0] $end
   $var wire  7 + vector_in[1] [6:0] $end
   $var wire  7 , vector_in[2] [6:0] $end
   $var wire  7 - vector_in[3] [6:0] $end
   $var wire  7 . vector_in[4] [6:0] $end
   $var wire  7 / vector_in[5] [6:0] $end
   $var wire  7 0 vector_in[6] [6:0] $end
   $var wire  7 1 vector_in[7] [6:0] $end
   $var wire  7 2 vector_in[8] [6:0] $end
   $var wire  7 3 vector_in[9] [6:0] $end
   $var wire 32 > vindx [31:0] $end
   $var wire  1 = y0 $end
   $var wire  1 ) y0_exp $end
   $var wire  1 < y1 $end
   $var wire  1 ( y1_exp $end
   $var wire  1 ; y2 $end
   $var wire  1 ' y2_exp $end
   $scope module dut $end
    $var wire  1 # a $end
    $var wire  1 $ b $end
    $var wire  1 % c $end
    $var wire  1 & d $end
    $var wire  1 = y0 $end
    $var wire  1 < y1 $end
    $var wire  1 ; y2 $end
   $upscope $end
   $scope module unnamedblk1 $end
    $var wire 32 : i [31:0] $end
   $upscope $end
  $upscope $end
 $upscope $end
$enddefinitions $end


#0
0#
0$
0%
0&
0'
1(
1)
b0000011 *
b0001011 +
b0010111 ,
b0011111 -
b0100011 .
b0101011 /
b0110011 0
b0111011 1
b1000001 2
b1001001 3
b1010101 4
b1011100 5
b1100000 6
b1101001 7
b1110100 8
b1111101 9
b00000000000000000000000000000000 :
0;
1<
1=
b00000000000000000000000000010000 >
#10
1&
b00000000000000000000000000000001 :
#20
1%
0&
1'
b00000000000000000000000000000010 :
1;
#30
1&
b00000000000000000000000000000011 :
#40
1$
0%
0&
0'
b00000000000000000000000000000100 :
0;
#50
1&
b00000000000000000000000000000101 :
#60
1%
0&
b00000000000000000000000000000110 :
#70
1&
b00000000000000000000000000000111 :
#80
1#
0$
0%
0&
0(
b00000000000000000000000000001000 :
0<
#90
1&
b00000000000000000000000000001001 :
#100
1%
0&
1'
b00000000000000000000000000001010 :
1;
#110
1&
0)
b00000000000000000000000000001011 :
0=
#120
1$
0%
0&
0'
b00000000000000000000000000001100 :
0;
#130
1&
1)
b00000000000000000000000000001101 :
1=
#140
1%
0&
1'
0)
b00000000000000000000000000001110 :
1;
0=
#150
1&
1)
b00000000000000000000000000001111 :
1=
#160
b00000000000000000000000000010000 :
