DDCA/Exercises/Chapter_5/Exercise_11/first_alu_32.sv
module first_alu_32
    (input logic[31:0] a,
    input logic[31:0] b,
    input logic[1:0] control,
    output logic[31:0] result);

    logic[31:0] sum;
    
    always_comb begin
        sum = a+((control[0]==1)?~b:b)+{31'b0,control[0]};
        case (control)
            2'b00 : result = sum;
            2'b01 : result = sum;
            2'b10 : result = a & b;
            2'b11 : result = a | b;
        endcase
    end
endmodule

DDCA/Exercises/Chapter_5/Exercise_11/tb_first_alu_32.sv
module tb_first_alu_32();
    localparam vindx = 10;
	logic[31:0] a, b;
    logic[1:0] control;
	logic[31:0] result, result_exp;
    logic[97:0] vector_in[0 : vindx - 1];

	first_alu_32 dut(.a(a), .b(b), .control(control), .result(result));

	initial begin
        $readmemh("input_first_alu_32.txt", vector_in);
        $dumpfile("waveform_tb_first_alu_32.vcd");
        $dumpvars(0, tb_first_alu_32);
        for(int i=0; i<vindx; i++) begin
            {control, a, b, result_exp} = vector_in[i]; #10;
            assert 
                (result === result_exp) 
            else 
                $error("Failed at line %d : a=%h, b=%h, control=%b, result=%h", (i+1), a, b, control, result);
        end
        $finish;
	end
endmodule

DDCA/Exercises/Chapter_5/Exercise_11/waveform_tb_first_alu_32.vcd
$version Generated by VerilatedVcd $end
$timescale 1ps $end

 $scope module TOP $end
  $scope module tb_first_alu_32 $end
   $var wire 32 # a [31:0] $end
   $var wire 32 $ b [31:0] $end
   $var wire  2 % control [1:0] $end
   $var wire 32 P result [31:0] $end
   $var wire 32 & result_exp [31:0] $end
   $var wire 98 ' vector_in[0] [97:0] $end
   $var wire 98 + vector_in[1] [97:0] $end
   $var wire 98 / vector_in[2] [97:0] $end
   $var wire 98 3 vector_in[3] [97:0] $end
   $var wire 98 7 vector_in[4] [97:0] $end
   $var wire 98 ; vector_in[5] [97:0] $end
   $var wire 98 ? vector_in[6] [97:0] $end
   $var wire 98 C vector_in[7] [97:0] $end
   $var wire 98 G vector_in[8] [97:0] $end
   $var wire 98 K vector_in[9] [97:0] $end
   $var wire 32 R vindx [31:0] $end
   $scope module dut $end
    $var wire 32 # a [31:0] $end
    $var wire 32 $ b [31:0] $end
    $var wire  2 % control [1:0] $end
    $var wire 32 P result [31:0] $end
    $var wire 32 Q sum [31:0] $end
   $upscope $end
   $scope module unnamedblk1 $end
    $var wire 32 O i [31:0] $end
   $upscope $end
  $upscope $end
 $upscope $end
$enddefinitions $end


#0
b00000000000000000000000011001000 #
b00000000000000000000000100101100 $
b00 %
b00000000000000000000000111110100 &
b00000000000000000000000000110010000000000000000000000000010010110000000000000000000000000111110100 '
b00111111111111111111111111001110001111111111111111111111101101010011111111111111111111111000001100 +
b00011111111111111111111111111111110111111111111111111111111111111111111111111111111111111111111110 /
b01000000000000000000000000110010000000000000000000000000010010110011111111111111111111111110011100 3
b01111111111111111111111111001110001111111111111111111111101101010000000000000000000000000001100100 7
b01011111111111111111111111111111111000000000000000000000000000000111111111111111111111111111111110 ;
b10110110101000010000010000111000001110011110100001010001101010100011000010100000000000000010100000 ?
b10110110101000010000010000111000000010010101111011111011110001111100000000000000000000000000000000 C
b11110110101000010000010000111000001110011110100001010001101010100011111111101001010101011011101000 G
b11110110101000010000010000111000000010010101111011111011110001111111111111111111111111111111111111 K
b00000000000000000000000000000000 O
b00000000000000000000000111110100 P
b00000000000000000000000111110100 Q
b00000000000000000000000000001010 R
#10
b11111111111111111111111100111000 #
b11111111111111111111111011010100 $
b11111111111111111111111000001100 &
b00000000000000000000000000000001 O
b11111111111111111111111000001100 P
b11111111111111111111111000001100 Q
#20
b01111111111111111111111111111111 #
b01111111111111111111111111111111 $
b11111111111111111111111111111110 &
b00000000000000000000000000000010 O
b11111111111111111111111111111110 P
b11111111111111111111111111111110 Q
#30
b00000000000000000000000011001000 #
b00000000000000000000000100101100 $
b01 %
b11111111111111111111111110011100 &
b00000000000000000000000000000011 O
b11111111111111111111111110011100 P
b11111111111111111111111110011100 Q
#40
b11111111111111111111111100111000 #
b11111111111111111111111011010100 $
b00000000000000000000000001100100 &
b00000000000000000000000000000100 O
b00000000000000000000000001100100 P
b00000000000000000000000001100100 Q
#50
b01111111111111111111111111111111 #
b10000000000000000000000000000001 $
b11111111111111111111111111111110 &
b00000000000000000000000000000101 O
b11111111111111111111111111111110 P
b11111111111111111111111111111110 Q
#60
b11011010100001000001000011100000 #
b11100111101000010100011010101000 $
b10 %
b11000010100000000000000010100000 &
b00000000000000000000000000000110 O
b11000010100000000000000010100000 P
b11000010001001010101011110001000 Q
#70
b00100101011110111110111100011111 $
b00000000000000000000000000000000 &
b00000000000000000000000000000111 O
b00000000000000000000000000000000 P
b11111111111111111111111111111111 Q
#80
b11100111101000010100011010101000 $
b11 %
b11111111101001010101011011101000 &
b00000000000000000000000000001000 O
b11111111101001010101011011101000 P
b11110010111000101100101000111000 Q
#90
b00100101011110111110111100011111 $
b11111111111111111111111111111111 &
b00000000000000000000000000001001 O
b11111111111111111111111111111111 P
b10110101000010000010000111000001 Q
#100
b00000000000000000000000000001010 O
