DDCA/Exercises/Chapter_5/Exercise_12/second_alu_32.sv
module second_alu_32
    (input logic[31:0] a,
    input logic[31:0] b,
    input logic[1:0] control,
    output logic[31:0] result,
    output logic[3:0] flags);
    
    logic N,Z,C,V;
    logic[31:0] sum;
    logic[32:0] ext_a, ext_b, ext_c;
    logic cout;

    always_comb begin
        ext_a = {a[31],a};
        ext_b = {b[31],b};
        ext_c = {32'b0,control[0]};
        {cout, sum} = ext_a+((control[0]==1)?~ext_b:ext_b)+ext_c;
        case (control)
            2'b00 : result = sum;
            2'b01 : result = sum;
            2'b10 : result = a & b;
            2'b11 : result = a | b;
            default : result = 32'bx;
        endcase
        N = result[31];
        Z = &(~result);
        C = ~control[1] & cout;
        V = ~(a[31] ^ b[31] ^ control[0]) & (a[31] ^ sum[31]) & ~control[1];
        flags = {N,Z,C,V};
    end
endmodule

DDCA/Exercises/Chapter_5/Exercise_12/tb_second_alu_32.sv
module tb_second_alu_32();
    localparam vindx = 10;
	logic[31:0] a, b;
    logic[1:0] control;
	logic[31:0] result, result_exp;
    logic[3:0] flags, flags_exp;
    logic[101:0] vector_in[0 : vindx - 1];

	second_alu_32 dut(.a(a), .b(b), .control(control), .result(result), .flags(flags));

	initial begin
        $readmemh("input_second_alu_32.txt", vector_in);
        $dumpfile("waveform_tb_second_alu_32.vcd");
        $dumpvars(0, tb_second_alu_32);
        for(int i=0; i<vindx; i++) begin
            {control, a, b, result_exp, flags_exp} = vector_in[i]; #10;
            assert 
                (result === result_exp && flags === flags_exp) 
            else 
                $error("Failed at line %d : a=%h, b=%h, control=%b, result=%h, flags=%b", (i+1), a, b, control, result, flags);
        end
        $finish;
	end
endmodule

DDCA/Exercises/Chapter_5/Exercise_12/waveform_tb_second_alu_32.vcd
$version Generated by VerilatedVcd $end
$timescale 1ps $end

 $scope module TOP $end
  $scope module tb_second_alu_32 $end
   $var wire 32 # a [31:0] $end
   $var wire 32 $ b [31:0] $end
   $var wire  2 % control [1:0] $end
   $var wire  4 R flags [3:0] $end
   $var wire  4 ' flags_exp [3:0] $end
   $var wire 32 Q result [31:0] $end
   $var wire 32 & result_exp [31:0] $end
   $var wire 102 ( vector_in[0] [101:0] $end
   $var wire 102 , vector_in[1] [101:0] $end
   $var wire 102 0 vector_in[2] [101:0] $end
   $var wire 102 4 vector_in[3] [101:0] $end
   $var wire 102 8 vector_in[4] [101:0] $end
   $var wire 102 < vector_in[5] [101:0] $end
   $var wire 102 @ vector_in[6] [101:0] $end
   $var wire 102 D vector_in[7] [101:0] $end
   $var wire 102 H vector_in[8] [101:0] $end
   $var wire 102 L vector_in[9] [101:0] $end
   $var wire 32 _ vindx [31:0] $end
   $scope module dut $end
    $var wire  1 U C $end
    $var wire  1 S N $end
    $var wire  1 V V $end
    $var wire  1 T Z $end
    $var wire 32 # a [31:0] $end
    $var wire 32 $ b [31:0] $end
    $var wire  2 % control [1:0] $end
    $var wire  1 ^ cout $end
    $var wire 33 X ext_a [32:0] $end
    $var wire 33 Z ext_b [32:0] $end
    $var wire 33 \ ext_c [32:0] $end
    $var wire  4 R flags [3:0] $end
    $var wire 32 Q result [31:0] $end
    $var wire 32 W sum [31:0] $end
   $upscope $end
   $scope module unnamedblk1 $end
    $var wire 32 P i [31:0] $end
   $upscope $end
  $upscope $end
 $upscope $end
$enddefinitions $end


#0
b00000000000000000000000011001000 #
b00000000000000000000000100101100 $
b00 %
b00000000000000000000000111110100 &
b0000 '
b000000000000000000000000001100100000000000000000000000000100101100000000000000000000000001111101000000 (
b001111111111111111111111110011100011111111111111111111111011010100111111111111111111111110000011001010 ,
b000111111111111111111111111111111101111111111111111111111111111111111111111111111111111111111111101001 0
b010000000000000000000000001100100000000000000000000000000100101100111111111111111111111111100111001010 4
b011111111111111111111111110011100011111111111111111111111011010100000000000000000000000000011001000000 8
b010111111111111111111111111111111110000000000000000000000000000001111111111111111111111111111111101001 <
b101101101010000100000100001110000011100111101000010100011010101000110000101000000000000000101000001000 @
b101101101010000100000100001110000000100101011110111110111100011111000000000000000000000000000000000100 D
b111101101010000100000100001110000011100111101000010100011010101000111111111010010101010110111010001000 H
b111101101010000100000100001110000000100101011110111110111100011111111111111111111111111111111111111000 L
b00000000000000000000000000000000 P
b00000000000000000000000111110100 Q
b0000 R
0S
0T
0U
0V
b00000000000000000000000111110100 W
b000000000000000000000000011001000 X
b000000000000000000000000100101100 Z
b000000000000000000000000000000000 \
0^
b00000000000000000000000000001010 _
#10
b11111111111111111111111100111000 #
b11111111111111111111111011010100 $
b11111111111111111111111000001100 &
b1010 '
b00000000000000000000000000000001 P
b11111111111111111111111000001100 Q
b1010 R
1S
1U
b11111111111111111111111000001100 W
b111111111111111111111111100111000 X
b111111111111111111111111011010100 Z
1^
#20
b01111111111111111111111111111111 #
b01111111111111111111111111111111 $
b11111111111111111111111111111110 &
b1001 '
b00000000000000000000000000000010 P
b11111111111111111111111111111110 Q
b1001 R
0U
1V
b11111111111111111111111111111110 W
b001111111111111111111111111111111 X
b001111111111111111111111111111111 Z
0^
#30
b00000000000000000000000011001000 #
b00000000000000000000000100101100 $
b01 %
b11111111111111111111111110011100 &
b1010 '
b00000000000000000000000000000011 P
b11111111111111111111111110011100 Q
b1010 R
1U
0V
b11111111111111111111111110011100 W
b000000000000000000000000011001000 X
b000000000000000000000000100101100 Z
b000000000000000000000000000000001 \
1^
#40
b11111111111111111111111100111000 #
b11111111111111111111111011010100 $
b00000000000000000000000001100100 &
b0000 '
b00000000000000000000000000000100 P
b00000000000000000000000001100100 Q
b0000 R
0S
0U
b00000000000000000000000001100100 W
b111111111111111111111111100111000 X
b111111111111111111111111011010100 Z
0^
#50
b01111111111111111111111111111111 #
b10000000000000000000000000000001 $
b11111111111111111111111111111110 &
b1001 '
b00000000000000000000000000000101 P
b11111111111111111111111111111110 Q
b1001 R
1S
1V
b11111111111111111111111111111110 W
b001111111111111111111111111111111 X
b110000000000000000000000000000001 Z
#60
b11011010100001000001000011100000 #
b11100111101000010100011010101000 $
b10 %
b11000010100000000000000010100000 &
b1000 '
b00000000000000000000000000000110 P
b11000010100000000000000010100000 Q
b1000 R
0V
b11000010001001010101011110001000 W
b111011010100001000001000011100000 X
b111100111101000010100011010101000 Z
b000000000000000000000000000000000 \
1^
#70
b00100101011110111110111100011111 $
b00000000000000000000000000000000 &
b0100 '
b00000000000000000000000000000111 P
b00000000000000000000000000000000 Q
b0100 R
0S
1T
b11111111111111111111111111111111 W
b000100101011110111110111100011111 Z
#80
b11100111101000010100011010101000 $
b11 %
b11111111101001010101011011101000 &
b1000 '
b00000000000000000000000000001000 P
b11111111101001010101011011101000 Q
b1000 R
1S
0T
b11110010111000101100101000111000 W
b111100111101000010100011010101000 Z
b000000000000000000000000000000001 \
#90
b00100101011110111110111100011111 $
b11111111111111111111111111111111 &
b00000000000000000000000000001001 P
b11111111111111111111111111111111 Q
b10110101000010000010000111000001 W
b000100101011110111110111100011111 Z
#100
b00000000000000000000000000001010 P
