DDCA/Exercises/Chapter_5/Exercise_04/prefix_adder.sv
/* verilator lint_off UNOPTFLAT */
module prefix_adder #(parameter N=4)
    (input logic [2**N-1:0] a, 
    input logic [2**N-1:0] b, 
    input logic cin, 
    output logic [2**N-1:0] s, 
    output logic cout);

    genvar i, j;

    logic[2**N-1:0] p[N:0];
    logic[2**N-1:0] g[N:0];

    assign p[0][0] = 0;
    assign g[0][0] = cin;

    generate
        for (j=0; j<2**N-1; j++) begin
            assign p[0][j+1] = a[j] | b[j];
            assign g[0][j+1] = a[j] & b[j];
        end

        for(i=1; i<N+1; i++) begin
            for (j=0; j<2**N; j++) begin
                if (j%2**i <= 2**(i+1) && j%2**i >= 2**(i-1)) begin
                    // j-1 are the selected column
                    // (j%(2**i)) set the pattern for power of 2
                    // (2**(i-1)) set offset from the right
                    assign p[i][j] = p[i-1][j] & p[i-1][j-1-(j%(2**i))+(2**(i-1))];
                    assign g[i][j] = g[i-1][j] | p[i-1][j] & g[i-1][j-1-(j%(2**i))+(2**(i-1))];
                end
                else begin
                    assign p[i][j] = p[i-1][j];
                    assign g[i][j] = g[i-1][j];
                end
            end
        end

        for (j=0; j<2**N; j++) begin
            assign s[j] = (a[j] ^ b[j]) ^ g[N][j];
        end

        assign cout = ((a[2**N-1] ^ b[2**N-1]) & g[N][2**N-1]) | (a[2**N-1] & b[2**N-1]);
    endgenerate
endmodule

DDCA/Exercises/Chapter_5/Exercise_04/tb_prefix_adder.sv
module tb_prefix_adder();
    localparam N=4;
    logic[2**N-1:0] a, b, s, s_exp;
    logic cin, cout, cout_exp;
    prefix_adder #(N) dut(.a(a), .b(b), .cin(cin), .s(s), .cout(cout));
    initial begin
		$dumpfile("waveform_prefix_adder.vcd");
		$dumpvars(0, tb_prefix_adder);
    end

    always begin
        for (integer i=0; i<=50; i++) begin
            a <= {$urandom}[2**N-1:0];
            b <= {$urandom}[2**N-1:0];
            cin <= {$random}[0];
            #10;
            {cout_exp, s_exp} = a + b + {{2**N-1{1'b0}}, cin};
            if(s !== s_exp || cout !== cout_exp) begin
                $display("Failed test at %d: a=%h, b=%h, cin=%b, s=%h, s_exp=%h, cout=%b, cout_exp=%b", (i+1), a, b, cin, s, s_exp, cout, cout_exp);
            end
        end
        $finish;
    end
endmodule

DDCA/Exercises/Chapter_5/Exercise_04/waveform_prefix_adder.vcd
$version Generated by VerilatedVcd $end
$timescale 1ps $end
 $scope module TOP $end
  $scope module tb_prefix_adder $end
   $var wire 32 5 N [31:0] $end
   $var wire 16 # a [15:0] $end
   $var wire 16 $ b [15:0] $end
   $var wire 16 & s [15:0] $end
   $var wire 16 ' s_exp [15:0] $end
   $var wire 1 % cin $end
   $var wire 1 ( cout $end
   $var wire 1 ) cout_exp $end
   $scope module dut $end
    $var wire 32 5 N [31:0] $end
    $var wire 16 # a [15:0] $end
    $var wire 16 $ b [15:0] $end
    $var wire 1 % cin $end
    $var wire 16 & s [15:0] $end
    $var wire 1 ( cout $end
    $var wire 16 * p[0] [15:0] $end
    $var wire 16 + p[1] [15:0] $end
    $var wire 16 , p[2] [15:0] $end
    $var wire 16 - p[3] [15:0] $end
    $var wire 16 . p[4] [15:0] $end
    $var wire 16 / g[0] [15:0] $end
    $var wire 16 0 g[1] [15:0] $end
    $var wire 16 1 g[2] [15:0] $end
    $var wire 16 2 g[3] [15:0] $end
    $var wire 16 3 g[4] [15:0] $end
   $upscope $end
   $scope module unnamedblk1 $end
    $var wire 32 4 i [31:0] $end
   $upscope $end
  $upscope $end
 $upscope $end
$enddefinitions $end


#0
b0000000000000000 #
b0000000000000000 $
0%
b0000000000000000 &
b0000000000000000 '
0(
0)
b0000000000000000 *
b0000000000000000 +
b0000000000000000 ,
b0000000000000000 -
b0000000000000000 .
b0000000000000000 /
b0000000000000000 0
b0000000000000000 1
b0000000000000000 2
b0000000000000000 3
b00000000000000000000000000000000 4
b00000000000000000000000000000100 5
#10
b1110000011100100 #
b1000001101111000 $
b0110010001011100 &
1(
b1100011111111000 *
b1100011111110000 +
b0000011111110000 ,
b0000011100000000 -
b0000000011000000 /
b0000000011000000 0
b0000000011000000 1
b0000000011000000 2
b0000011111000000 3
b00000000000000000000000000000001 4
#20
b1001111010110110 #
b1111111111100100 $
1%
b1001111010011011 &
b0110010001011100 '
1)
b1111111111101100 *
b1111111111001100 +
b1111111100000000 ,
b1111111100000000 -
b0011110101001001 /
b0011111111001001 0
b1111111111001001 1
b1111111111001001 2
b1111111111001001 3
b00000000000000000000000000000010 4
#30
b0111000101010011 #
b0001011100100001 $
b1000100001110101 &
b1001111010011011 '
0(
b1110111011100110 *
b1100110011000100 +
b0000000000000000 ,
b0000000000000000 -
b0010001000000011 /
b0010001000000011 0
b1110111000000111 1
b1110111000000111 2
b1110111000000111 3
b00000000000000000000000000000011 4
#40
b1010111111000101 #
b1111001110000010 $
0%
b1010001101000111 &
b1000100001110101 '
1(
0)
b1111111110001110 *
b1111111100001100 +
b1111111100000000 ,
b1111111100000000 -
b0100011100000000 /
b1100111100000000 0
b1100111100000000 1
b1111111100000000 2
b1111111100000000 3
b00000000000000000000000000000100 4
#50
b0001011000110101 #
b1100100100010010 $
b1101111101000111 &
b1010001101000111 '
0(
1)
b1011111001101110 *
b0011110001001100 +
b0011000000000000 ,
b0000000000000000 -
b0000000000100000 /
b0000000000100000 0
b0000000001100000 1
b0000000001100000 2
b0000000001100000 3
b00000000000000000000000000000101 4
#60
b0011101111111101 #
b0100000111110100 $
1%
b0111110111110010 &
b1101111101000111 '
0)
b1111011111111010 *
b1111011111110000 +
b1111011111110000 ,
b0000011100000000 -
b0000001111101001 /
b0000001111101011 0
b0000011111101011 1
b0000011111111011 2
b0000011111111011 3
b00000000000000000000000000000110 4
#70
b0100110101011000 #
b0000010010110010 $
0%
b0101001000001010 &
b0111110111110010 '
b1001101111110100 *
b0001001111110100 +
b0001001111110000 ,
b0000001100000000 -
b0000100000100000 /
b0000100000100000 0
b0000100011100000 1
b0001100011100000 2
b0001101111100000 3
b00000000000000000000000000000111 4
#80
b1000010100011110 #
b0100010110011110 $
b1100101010111100 &
b0101001000001010 '
b1000101100111100 *
b0000001100111100 +
b0000001100110000 ,
b0000101000111100 /
b0000101000111100 0
b0000101000111100 1
b0000101000111100 2
b0000101000111100 3
b00000000000000000000000000001000 4
#90
b0001110011101110 #
b0110101100010000 $
b1000011111111110 &
b1100101010111100 '
b1111111111111100 *
b1111111111111100 +
b1111111111110000 ,
b1111111100000000 -
b0001000000000000 /
b0011000000000000 0
b1111000000000000 1
b1111000000000000 2
b1111000000000000 3
b00000000000000000000000000001001 4
#100
b1110110101100011 #
b1010001011000000 $
1%
b1001000000100100 &
b1000011111111110 '
1(
b1101111111000110 *
b1101111111000100 +
b0001111100000000 ,
b0001111100000000 -
b0100000010000001 /
b1100000010000011 0
b1100000010000111 1
b1100000010000111 2
b1101111110000111 3
b00000000000000000000000000001010 4
#110
b0000111100100010 #
b1000111100000110 $
b1001111000101001 &
b1001000000100100 '
0(
1)
b0001111001001100 *
b0001110001001100 +
b0001000000000000 ,
b0000000000000000 -
b0001111000000101 /
b0001111000001101 0
b0001111000001101 1
b0001111000001101 2
b0001111000001101 3
b00000000000000000000000000001011 4
#120
b0011001001100011 #
b1100001001111000 $
b1111010011011100 &
b1001111000101001 '
0)
b1110010011110110 *
b1100010011110100 +
b0000000011110000 ,
b0000010011000001 /
b0000010011000011 0
b0000010011000111 1
b0000010011000111 2
b0000010011000111 3
b00000000000000000000000000001100 4
#130
b1101101011001110 #
b1111111011110111 $
b1101100111000110 &
b1111010011011100 '
1(
b1111110111111110 *
b1111110111111100 +
b1111000111110000 ,
b0000000100000000 -
b1011010110001101 /
b1011110110001111 0
b1111110110001111 1
b1111110111111111 2
b1111110111111111 3
b00000000000000000000000000001101 4
#140
b1011001110011110 #
b1101100001110111 $
0%
b1000110000010101 &
b1101100111000110 '
1)
b1111011111111110 *
b1111011111111100 +
b1111011111110000 ,
b0000011100000000 -
b0010000000101100 /
b0010000000101100 0
b1110000011101100 1
b1110000011111100 2
b1110011111111100 3
b00000000000000000000000000001110 4
#150
b0000110010101000 #
b1110001101001111 $
1%
b1110111111111000 &
b1000110000010101 '
0(
b1101111111011110 *
b1101111111011100 +
b0001111100010000 ,
b0001111100000000 -
b0000000000010001 /
b0000000000010011 0
b0000000000011111 1
b0000000000011111 2
b0000000000011111 3
b00000000000000000000000000001111 4
#160
b1000100110010100 #
b0010111011100010 $
0%
b1011100001110110 &
b1110111111111000 '
0)
b0101111111101100 *
b0101111111001100 +
b0001111100000000 ,
b0001000100000000 /
b0001001100000000 0
b0001111100000000 1
b0001111100000000 2
b0001111100000000 3
b00000000000000000000000000010000 4
#170
b0001101100011111 #
b1011001100001001 $
1%
b1100111000101001 &
b1011100001110110 '
b0111011000111110 *
b0111010000111100 +
b0111000000110000 ,
b0000000000000000 -
b0010011000010011 /
b0010011000110011 0
b0110011000111111 1
b0110011000111111 2
b0110011000111111 3
b00000000000000000000000000010001 4
#180
b1111011000011111 #
b1010111110000100 $
b1010010110100100 &
b1100111000101001 '
1(
b1111111100111110 *
b1111111100111100 +
b1111111100110000 ,
b1111111100000000 -
b0100110000001001 /
b1100110000001011 0
b1100110000001111 1
b1111110000111111 2
b1111110000111111 3
b00000000000000000000000000010010 4
#190
b1010011000110011 #
b1110101001001011 $
0%
b1001000001111110 &
b1010010110100100 '
1)
b1101110011110110 *
b1101110011110100 +
b0001000011110000 ,
b0000000000000000 -
b0100010000000110 /
b1100110000000110 0
b1100110000000110 1
b1101110000000110 2
b1101110000000110 3
b00000000000000000000000000010011 4
#200
b1010100011110011 #
b0010110011001001 $
1%
b1101010110111101 &
b1001000001111110 '
0(
b0101100111110110 *
b0101000111110100 +
b0001000111110000 ,
b0000000100000000 -
b0101000110000011 /
b0101000110000011 0
b0101000110000111 1
b0101000110000111 2
b0101000110000111 3
b00000000000000000000000000010100 4
#210
b0110010111001010 #
b1101010101011101 $
b0011101100101000 &
b1101010110111101 '
1(
0)
b1110101110111110 *
b1100001100111100 +
b0000001100110000 ,
b0000001100000000 -
b1000101010010001 /
b1000101010110011 0
b1000101010111111 1
b1000101010111111 2
b1000101110111111 3
b00000000000000000000000000010101 4
#220
b1110110100100100 #
b1011001011101111 $
b1010000000010100 &
b0011101100101000 '
1)
b1111111111011110 *
b1111111111011100 +
b1111111100010000 ,
b1111111100000000 -
b0100000001001001 /
b1100000011001011 0
b1100000011001111 1
b1100000011011111 2
b1111111111011111 3
b00000000000000000000000000010110 4
#230
b1101100101101101 #
b0011011100111001 $
0%
b0001000010100110 &
b1010000000010100 '
b1111111011111010 *
b1111110011110000 +
b1111000011110000 ,
b0000000000000000 -
b0010001001010010 /
b0010001011110010 0
b1110111011110010 1
b1111111011110010 2
b1111111011110010 3
b00000000000000000000000000010111 4
#240
b1110100011101010 #
b0011100011000010 $
b0010000110101100 &
b0001000010100110 '
b1111000111010100 *
b1111000111010100 +
b1111000100010000 ,
b0000000100000000 -
b0101000110000100 /
b1111000110000100 0
b1111000110000100 1
b1111000110000100 2
b1111000110000100 3
b00000000000000000000000000011000 4
#250
b0100100101010100 #
b1100101100100011 $
1%
b0001010001111000 &
b0010000110101100 '
b1001011011101110 *
b0001010011001100 +
b0001000000000000 ,
b0000000000000000 -
b1001001000000001 /
b1001001000000011 0
b1001011000001111 1
b1001011000001111 2
b1001011000001111 3
b00000000000000000000000000011001 4
#260
b0100001110110011 #
b0111111110101101 $
b1100001101100001 &
b0001010001111000 '
0(
b1111111101111110 *
b1111111101111100 +
b1111111101110000 ,
b1111111100000000 -
b1000011101000011 /
b1000111101000011 0
b1000111101001111 1
b1111111101111111 2
b1111111101111111 3
b00000000000000000000000000011010 4
#270
b0111101100101110 #
b1011100011001111 $
b0011001111111110 &
b1100001101100001 '
1(
0)
b1111011111011110 *
b1111011111011100 +
b1111011100010000 ,
b0000011100000000 -
b0111000000011101 /
b1111000000011111 0
b1111000000011111 1
b1111000000011111 2
b1111000000011111 3
b00000000000000000000000000011011 4
#280
b1001010111010111 #
b0000010010001001 $
0%
b1001101001100000 &
b0011001111111110 '
0(
1)
b0010101110111110 *
b0000001100111100 +
b0000001100110000 ,
b0000001100000000 -
b0000100100000010 /
b0000101100000010 0
b0000101100001110 1
b0000101100111110 2
b0000101100111110 3
b00000000000000000000000000011100 4
#290
b1001111110101111 #
b1111010111101111 $
1%
b1001010110011111 &
b1001101001100000 '
1(
0)
b1111111111011110 *
b1111111111011100 +
b1111111100010000 ,
b1111111100000000 -
b0010101101011111 /
b0010101111011111 0
b1110111111011111 1
b1111111111011111 2
b1111111111011111 3
b00000000000000000000000000011101 4
#300
b0100001100111111 #
b1100111011001111 $
0%
b0001001000001110 &
b1001010110011111 '
1)
b1001111111111110 *
b0001111111111100 +
b0001111111110000 ,
b0001111100000000 -
b1000010000011110 /
b1000110000111110 0
b1000110011111110 1
b1001110011111110 2
b1001111111111110 3
b00000000000000000000000000011110 4
#310
b1110001101110111 #
b1001101010011010 $
1%
b0111111000010010 &
b0001001000001110 '
b1111011111111110 *
b1111011111111100 +
b1111011111110000 ,
b0000011100000000 -
b0000010000100101 /
b0000010000101111 0
b0000010011101111 1
b0000010011111111 2
b0000011111111111 3
b00000000000000000000000000011111 4
#320
b0001111101010011 #
b0100001010101111 $
0%
b0110001000000010 &
b0111111000010010 '
0(
b1011111111111110 *
b0011111111111100 +
b0011111111110000 ,
b0011111100000000 -
b0000010000000110 /
b0000110000001110 0
b0000110000001110 1
b0011110011111110 2
b0011111111111110 3
b00000000000000000000000000100000 4
#330
b1011001100000010 #
b0010101111111011 $
b1101111011111101 &
b0110001000000010 '
0)
b0111011111110110 *
b0111011111110100 +
b0111011111110000 ,
b0000011100000000 -
b0100011000000100 /
b0100011000000100 0
b0100011000000100 1
b0100011000000100 2
b0100011000000100 3
b00000000000000000000000000100001 4
#340
b1101100111000010 #
b1100110111011101 $
b1010011110011111 &
b1101111011111101 '
1(
b1011101110111110 *
b0011001100111100 +
b0011001100110000 ,
b0000001100000000 -
b1001001110000000 /
b1011001110000000 0
b1011001110000000 1
b1011001110000000 2
b1011001110000000 3
b00000000000000000000000000100010 4
#350
b1101100001100100 #
b1010011001100001 $
1%
b0111111011000110 &
b1010011110011111 '
1)
b1111110011001010 *
b1111110011000000 +
b1111000000000000 ,
b0000000000000000 -
b0000000011000001 /
b0000000011000011 0
b0000000011000011 1
b0000000011000011 2
b0000000011000011 3
b00000000000000000000000000100011 4
#360
b1101110100100001 #
b0010011111110011 $
b0000010100010101 &
b0111111011000110 '
b1111111111100110 *
b1111111111000100 +
b1111111100000000 ,
b1111111100000000 -
b0000101001000011 /
b0000101011000011 0
b0000111011000111 1
b1111111011000111 2
b1111111111000111 3
b00000000000000000000000000100100 4
#370
b0001100011110101 #
b0001011010111101 $
0%
b0010111110110010 &
b0000010100010101 '
0(
b0011110111111010 *
b0011110111110000 +
b0011000111110000 ,
b0000000100000000 -
b0010000101101010 /
b0010000111101010 0
b0010000111101010 1
b0010000111111010 2
b0010000111111010 3
b00000000000000000000000000100101 4
#380
b0010011001100010 #
b1001111111001010 $
b1100011000101100 &
b0010111110110010 '
0)
b0111111111010100 *
b0111111111010100 +
b0111111100010000 ,
b0111111100000000 -
b0000110010000100 /
b0000110010000100 0
b0000110010000100 1
b0111110010000100 2
b0111111110000100 3
b00000000000000000000000000100110 4
#390
b1100011101000101 #
b1110000001011000 $
b1010011110011101 &
b1100011000101100 '
1(
b1100111010111010 *
b1100110000110000 +
b0000000000110000 ,
b0000000000000000 -
b1000000010000000 /
b1000000010000000 0
b1000000010000000 1
b1000000010000000 2
b1000000010000000 3
b00000000000000000000000000100111 4
#400
b1101111001100000 #
b0000001101110011 $
b1110000111010011 &
b1010011110011101 '
0(
1)
b1011111011100110 *
b0011110011000100 +
b0011000000000000 ,
b0000010011000000 /
b0000110011000000 0
b0000110011000000 1
b0011110011000000 2
b0011110011000000 3
b00000000000000000000000000101000 4
#410
b1100000100111101 #
b1010010001101100 $
b0110010110101001 &
b1110000111010011 '
1(
0)
b1100101011111010 *
b1100000011110000 +
b0000000011110000 ,
b0000000001011000 /
b0000000011111000 0
b0000000011111000 1
b0000000011111000 2
b0000000011111000 3
b00000000000000000000000000101001 4
#420
b1001101011100111 #
b0101001000110111 $
1%
b1110110100011111 &
b0110010110101001 '
0(
1)
b1011010111101110 *
b0011010111001100 +
b0011000100000000 ,
b0000000100000000 -
b0010010001001111 /
b0010010011001111 0
b0010010011001111 1
b0010010011001111 2
b0010010111001111 3
b00000000000000000000000000101010 4
#430
b1001001101000000 #
b0100100000110011 $
0%
b1101101101110011 &
b1110110100011111 '
0)
b1011011011100110 *
b0011010011000100 +
b0011000000000000 ,
b0000000000000000 -
b0000000000000000 /
b0000000000000000 0
b0000000000000000 1
b0000000000000000 2
b0000000000000000 3
b00000000000000000000000000101011 4
#440
b0001101010110110 #
b1110001011010111 $
b1111110110001101 &
b1101101101110011 '
b1111010111101110 *
b1111010111001100 +
b1111000100000000 ,
b0000000100000000 -
b0000010100101100 /
b0000010100101100 0
b0000010111101100 1
b0000010111101100 2
b0000010111101100 3
b00000000000000000000000000101100 4
#450
b0100101001100111 #
b1111011001010011 $
b0100000010111010 &
b1111110110001101 '
1(
b1111110011101110 *
b1111110011001100 +
b1111000000000000 ,
b0000000000000000 -
b1000010010000110 /
b1000110010001110 0
b1000110010001110 1
b1111110010001110 2
b1111110010001110 3
b00000000000000000000000000101101 4
#460
b1110100011110100 #
b1000011011100100 $
b0110111111011000 &
b0100000010111010 '
1)
b1101110111101000 *
b1101110111000000 +
b0001000100000000 ,
b0000000100000000 -
b0000000111001000 /
b0000000111001000 0
b0000000111001000 1
b0000000111001000 2
b0000000111001000 3
b00000000000000000000000000101110 4
#470
b0100001101100111 #
b1101100010010101 $
b0001101111111100 &
b0110111111011000 '
b1011011111101110 *
b0011011111001100 +
b0011011100000000 ,
b0000011100000000 -
b1000000000001010 /
b1000000000001010 0
b1000000000001110 1
b1000000000001110 2
b1000000000001110 3
b00000000000000000000000000101111 4
#480
b0001101101100100 #
b0100000110010101 $
b0101110011111001 &
b0001101111111100 '
0(
b1011011111101010 *
b0011011111000000 +
b0000001000001000 /
b0000001000001000 0
b0000011000001000 1
b0000011000001000 2
b0000011000001000 3
b00000000000000000000000000110000 4
#490
b0100011100111101 #
b0111000001111111 $
1%
b1011011110111101 &
b0101110011111001 '
0)
b1110111011111110 *
b1100110011111100 +
b0000000011110000 ,
b0000000000000000 -
b1000000001111011 /
b1000000011111011 0
b1000000011111111 1
b1000000011111111 2
b1000000011111111 3
b00000000000000000000000000110001 4
#500
b1010100011011100 #
b1100101111101100 $
0%
b0111010011001000 &
b1011011110111101 '
1(
b1101011111111000 *
b1101011111110000 +
b0001011111110000 ,
b0000011100000000 -
b0001000110011000 /
b0001001110111000 0
b0001011111111000 1
b0001011111111000 2
b0001011111111000 3
b00000000000000000000000000110010 4
#510
b0000000001000110 #
b1111000001111001 $
b1111000010111111 &
b0111010011001000 '
0(
1)
b1110000011111110 *
b1100000011111100 +
b0000000011110000 ,
b0000000000000000 -
b0000000010000000 /
b0000000010000000 0
b0000000010000000 1
b0000000010000000 2
b0000000010000000 3
b00000000000000000000000000110011 4
