DDCA/Exercises/Chapter_5/Exercise_55/scan_reg.sv
module scan_reg
    #(parameter N=4)
    (input logic[N-1:0] d,
    input logic sin,
    input logic clk,
    input logic test,
    output logic sout,
    output logic[N-1:0] q);

    logic[N-1:0] chain;
    always_ff @(posedge clk) begin
        chain[0] <= (test == 1'b1) ? d[0] : sin;
        for(integer i=1; i<N; i++) begin
            chain[i] <= (test == 1'b1) ? d[i] : chain[i-1];
        end
        sout <= chain[N-1];
        q <= chain;
    end
endmodule

DDCA/Exercises/Chapter_5/Exercise_55/tb_scan_reg.sv
module tb_scan_reg();
    integer vindx;
    localparam top = 6;
    logic[3:0] d;
    logic clk, test, sin;
    logic[3:0] q, q_exp;
    logic sout, sout_exp;
    logic[10:0] vector_in[0 : top - 1];

	scan_reg #(4) dut(.clk(clk), .d(d), .sin(sin), .test(test), .q(q), .sout(sout));

	initial begin
        $readmemb("input_scan_reg.txt", vector_in);
        $dumpfile("waveform_scan_reg.vcd");
        $dumpvars(0, tb_scan_reg);
        vindx=0;
	end

    always begin
        clk = 0; #10;
        clk = 1; #10;
    end

    always @(posedge clk) begin
        {d, sin, test, q_exp, sout_exp} = vector_in[vindx];
    end

    always @(negedge clk) begin
        assert 
            (q === q_exp && sout === sout_exp)
        else 
            $error("Failed at line %d : d=%b, q=%b, (sin, sout) = %b", vindx, d, q, {sin, sout});
        vindx++;
        if (vindx >= top) begin
            $finish;
        end
    end
endmodule

DDCA/Exercises/Chapter_5/Exercise_55/waveform_scan_reg.vcd
$version Generated by VerilatedVcd $end
$timescale 1ps $end

 $scope module TOP $end
  $scope module tb_scan_reg $end
   $var wire  1 3 clk $end
   $var wire  4 ) d [3:0] $end
   $var wire  4 , q [3:0] $end
   $var wire  4 - q_exp [3:0] $end
   $var wire  1 + sin $end
   $var wire  1 . sout $end
   $var wire  1 / sout_exp $end
   $var wire  1 * test $end
   $var wire 32 4 top [31:0] $end
   $var wire 11 # vector_in[0] [10:0] $end
   $var wire 11 $ vector_in[1] [10:0] $end
   $var wire 11 % vector_in[2] [10:0] $end
   $var wire 11 & vector_in[3] [10:0] $end
   $var wire 11 ' vector_in[4] [10:0] $end
   $var wire 11 ( vector_in[5] [10:0] $end
   $var wire 32 2 vindx [31:0] $end
   $scope module dut $end
    $var wire 32 5 N [31:0] $end
    $var wire  4 0 chain [3:0] $end
    $var wire  1 3 clk $end
    $var wire  4 ) d [3:0] $end
    $var wire  4 , q [3:0] $end
    $var wire  1 + sin $end
    $var wire  1 . sout $end
    $var wire  1 * test $end
    $scope module unnamedblk1 $end
     $var wire 32 1 i [31:0] $end
    $upscope $end
   $upscope $end
  $upscope $end
 $upscope $end
$enddefinitions $end


#0
b00001000000 #
b00000000010 $
b00001000100 %
b00001001010 &
b10010110111 '
b10010110011 (
b0000 )
0*
0+
b0000 ,
b0000 -
0.
0/
b0000 0
b00000000000000000000000000000000 1
b00000000000000000000000000000000 2
03
b00000000000000000000000000000110 4
b00000000000000000000000000000100 5
#10
1+
b0001 0
b00000000000000000000000000000100 1
13
#20
b00000000000000000000000000000001 2
03
#30
0+
b0001 ,
b0001 -
b0010 0
13
#40
b00000000000000000000000000000010 2
03
#50
1+
b0010 ,
b0010 -
b0101 0
13
#60
b00000000000000000000000000000011 2
03
#70
b0101 ,
b0101 -
b1011 0
13
#80
b00000000000000000000000000000100 2
03
#90
b1001 )
1*
0+
b1011 ,
b1011 -
1.
1/
b1001 0
13
#100
b00000000000000000000000000000101 2
03
#110
b1001 ,
b1001 -
13
#120
b00000000000000000000000000000110 2
03
