DDCA/Exercises/Chapter_4/Exercise_06/seven_seg.sv
module seven_seg 
    (input logic[3:0] data,
    output logic[6:0] seg);

    always_comb begin
        case(data)
            'h0 : seg = 7'b1111110;
            'h1 : seg = 7'b0110000;
            'h2 : seg = 7'b1101101;
            'h3 : seg = 7'b1111001;
            'h4 : seg = 7'b0110011;
            'h5 : seg = 7'b1011011;
            'h6 : seg = 7'b1011111;
            'h7 : seg = 7'b1110000;
            'h8 : seg = 7'b1111111;
            'h9 : seg = 7'b1111011;
            'hA : seg = 7'b1110111;
            'hB : seg = 7'b0011111;
            'hC : seg = 7'b1001110;
            'hD : seg = 7'b0111101;
            'hE : seg = 7'b1001111;
            'hF : seg = 7'b1000111;
        endcase
    end
endmodule

DDCA/Exercises/Chapter_4/Exercise_06/tb_seven_seg.sv
module tb_seven_seg();
    localparam vindx = 16;
    logic[3:0] data;
    logic[6:0] seg, seg_exp;
    logic[10:0] vector_in[0 : vindx - 1];
    seven_seg dut(.data(data), .seg(seg));
    initial
    begin
        $readmemb("input_seven_seg.txt", vector_in);
        $dumpfile("waveform_seven_seg.vcd");
        $dumpvars(0, tb_seven_seg);
        for (integer i=0; i < vindx; i++)
        begin
            {data, seg_exp} = vector_in[i]; #10;
            assert (seg === seg_exp) else $error("Failed at line %d : input %b output %b", (i+1), data, seg);
        end
    end
endmodule

DDCA/Exercises/Chapter_4/Exercise_06/waveform_seven_seg.vcd
$version Generated by VerilatedVcd $end
$timescale 1ps $end

 $scope module TOP $end
  $scope module tb_seven_seg $end
   $var wire  4 # data [3:0] $end
   $var wire  7 6 seg [6:0] $end
   $var wire  7 $ seg_exp [6:0] $end
   $var wire 11 % vector_in[0] [10:0] $end
   $var wire 11 / vector_in[10] [10:0] $end
   $var wire 11 0 vector_in[11] [10:0] $end
   $var wire 11 1 vector_in[12] [10:0] $end
   $var wire 11 2 vector_in[13] [10:0] $end
   $var wire 11 3 vector_in[14] [10:0] $end
   $var wire 11 4 vector_in[15] [10:0] $end
   $var wire 11 & vector_in[1] [10:0] $end
   $var wire 11 ' vector_in[2] [10:0] $end
   $var wire 11 ( vector_in[3] [10:0] $end
   $var wire 11 ) vector_in[4] [10:0] $end
   $var wire 11 * vector_in[5] [10:0] $end
   $var wire 11 + vector_in[6] [10:0] $end
   $var wire 11 , vector_in[7] [10:0] $end
   $var wire 11 - vector_in[8] [10:0] $end
   $var wire 11 . vector_in[9] [10:0] $end
   $var wire 32 7 vindx [31:0] $end
   $scope module dut $end
    $var wire  4 # data [3:0] $end
    $var wire  7 6 seg [6:0] $end
   $upscope $end
   $scope module unnamedblk1 $end
    $var wire 32 5 i [31:0] $end
   $upscope $end
  $upscope $end
 $upscope $end
$enddefinitions $end


#0
b0000 #
b1111110 $
b00001111110 %
b00010110000 &
b00101101101 '
b00111111001 (
b01000110011 )
b01011011011 *
b01101011111 +
b01111110000 ,
b10001111111 -
b10011111011 .
b10101110111 /
b10110011111 0
b11001001110 1
b11010111101 2
b11101001111 3
b11111000111 4
b00000000000000000000000000000000 5
b1111110 6
b00000000000000000000000000010000 7
#10
b0001 #
b0110000 $
b00000000000000000000000000000001 5
b0110000 6
#20
b0010 #
b1101101 $
b00000000000000000000000000000010 5
b1101101 6
#30
b0011 #
b1111001 $
b00000000000000000000000000000011 5
b1111001 6
#40
b0100 #
b0110011 $
b00000000000000000000000000000100 5
b0110011 6
#50
b0101 #
b1011011 $
b00000000000000000000000000000101 5
b1011011 6
#60
b0110 #
b1011111 $
b00000000000000000000000000000110 5
b1011111 6
#70
b0111 #
b1110000 $
b00000000000000000000000000000111 5
b1110000 6
#80
b1000 #
b1111111 $
b00000000000000000000000000001000 5
b1111111 6
#90
b1001 #
b1111011 $
b00000000000000000000000000001001 5
b1111011 6
#100
b1010 #
b1110111 $
b00000000000000000000000000001010 5
b1110111 6
#110
b1011 #
b0011111 $
b00000000000000000000000000001011 5
b0011111 6
#120
b1100 #
b1001110 $
b00000000000000000000000000001100 5
b1001110 6
#130
b1101 #
b0111101 $
b00000000000000000000000000001101 5
b0111101 6
#140
b1110 #
b1001111 $
b00000000000000000000000000001110 5
b1001111 6
#150
b1111 #
b1000111 $
b00000000000000000000000000001111 5
b1000111 6
#160
b00000000000000000000000000010000 5
