DDCA/Exercises/Chapter_4/Exercise_22/thermometer.sv
module thermometer
	#(parameter N = 3) 
	(input logic[N-1:0] a,
	output logic[2**N-1:0] y);

	always_comb begin
		y = 'b0;
		for(integer i = {{32-N{1'b0}}, a}; i >= 0; i--) begin
			y[i] = 1'b1;
		end
	end 
endmodule

DDCA/Exercises/Chapter_4/Exercise_22/tb_thermometer.sv
module tb_thermometer();
	localparam vindx = 8;
	logic[2:0] a;
	logic[7:0] y, y_exp;
	logic[10:0] vector_in[0 : vindx - 1];
	thermometer dut(.a(a), .y(y));
	initial
	begin
		$readmemb("input_thermometer.txt", vector_in);
		$dumpfile("waveform_thermometer.vcd");
		$dumpvars(0, tb_thermometer);
		for (integer i=0; i < vindx; i++)
		begin
			{a, y_exp} = vector_in[i]; #10;
			assert (y === y_exp) else $error("Failed at line %d : input %b output %b", (i+1), a, y);
		end
	end
endmodule

DDCA/Exercises/Chapter_4/Exercise_22/waveform_thermometer.vcd
$version Generated by VerilatedVcd $end
$timescale 1ps $end

 $scope module TOP $end
  $scope module tb_thermometer $end
   $var wire  3 # a [2:0] $end
   $var wire 11 % vector_in[0] [10:0] $end
   $var wire 11 & vector_in[1] [10:0] $end
   $var wire 11 ' vector_in[2] [10:0] $end
   $var wire 11 ( vector_in[3] [10:0] $end
   $var wire 11 ) vector_in[4] [10:0] $end
   $var wire 11 * vector_in[5] [10:0] $end
   $var wire 11 + vector_in[6] [10:0] $end
   $var wire 11 , vector_in[7] [10:0] $end
   $var wire 32 0 vindx [31:0] $end
   $var wire  8 . y [7:0] $end
   $var wire  8 $ y_exp [7:0] $end
   $scope module dut $end
    $var wire 32 1 N [31:0] $end
    $var wire  3 # a [2:0] $end
    $var wire  8 . y [7:0] $end
    $scope module unnamedblk1 $end
     $var wire 32 / i [31:0] $end
    $upscope $end
   $upscope $end
   $scope module unnamedblk1 $end
    $var wire 32 - i [31:0] $end
   $upscope $end
  $upscope $end
 $upscope $end
$enddefinitions $end


#0
b111 #
b11111111 $
b11111111111 %
b11001111111 &
b10100111111 '
b10000011111 (
b01100001111 )
b01000000111 *
b00100000011 +
b00000000001 ,
b00000000000000000000000000000000 -
b11111111 .
b11111111111111111111111111111111 /
b00000000000000000000000000001000 0
b00000000000000000000000000000011 1
#10
b110 #
b01111111 $
b00000000000000000000000000000001 -
b01111111 .
#20
b101 #
b00111111 $
b00000000000000000000000000000010 -
b00111111 .
#30
b100 #
b00011111 $
b00000000000000000000000000000011 -
b00011111 .
#40
b011 #
b00001111 $
b00000000000000000000000000000100 -
b00001111 .
#50
b010 #
b00000111 $
b00000000000000000000000000000101 -
b00000111 .
#60
b001 #
b00000011 $
b00000000000000000000000000000110 -
b00000011 .
#70
b000 #
b00000001 $
b00000000000000000000000000000111 -
b00000001 .
#80
b00000000000000000000000000001000 -
