DDCA/Exercises/Chapter_5/Exercise_30/zero_extended.sv
module zero_extended #(parameter N=4, M=8)
    (input logic[N-1:0] a,
    output logic[M-1:0] y);

    assign y = {{(M-N){1'b0}}, a[N-1:0]};
endmodule

DDCA/Exercises/Chapter_5/Exercise_30/tb_zero_extended.sv
module tb_zero_extended();
    localparam vindx = 16;
	logic[3:0] a;
	logic[7:0] y, y_exp;
    logic[11:0] vector_in[0 : vindx - 1];

	zero_extended #(4, 8) dut(.a(a), .y(y));

	initial begin
        $readmemb("input_zero_extended.txt", vector_in);
        $dumpfile("waveform_tb_zero_extended.vcd");
        $dumpvars(0, tb_zero_extended);
        for(int i=0; i<vindx; i++) begin
            {a, y_exp} = vector_in[i]; #10;
            assert 
                (y === y_exp) 
            else 
                $error("Failed at line %d : a=%b, y=%b", (i+1), a, y);
        end
        $finish;
	end
endmodule

DDCA/Exercises/Chapter_5/Exercise_30/waveform_tb_zero_extended.vcd
$version Generated by VerilatedVcd $end
$timescale 1ps $end

 $scope module TOP $end
  $scope module tb_zero_extended $end
   $var wire  4 # a [3:0] $end
   $var wire 12 & vector_in[0] [11:0] $end
   $var wire 12 0 vector_in[10] [11:0] $end
   $var wire 12 1 vector_in[11] [11:0] $end
   $var wire 12 2 vector_in[12] [11:0] $end
   $var wire 12 3 vector_in[13] [11:0] $end
   $var wire 12 4 vector_in[14] [11:0] $end
   $var wire 12 5 vector_in[15] [11:0] $end
   $var wire 12 ' vector_in[1] [11:0] $end
   $var wire 12 ( vector_in[2] [11:0] $end
   $var wire 12 ) vector_in[3] [11:0] $end
   $var wire 12 * vector_in[4] [11:0] $end
   $var wire 12 + vector_in[5] [11:0] $end
   $var wire 12 , vector_in[6] [11:0] $end
   $var wire 12 - vector_in[7] [11:0] $end
   $var wire 12 . vector_in[8] [11:0] $end
   $var wire 12 / vector_in[9] [11:0] $end
   $var wire 32 7 vindx [31:0] $end
   $var wire  8 $ y [7:0] $end
   $var wire  8 % y_exp [7:0] $end
   $scope module dut $end
    $var wire 32 9 M [31:0] $end
    $var wire 32 8 N [31:0] $end
    $var wire  4 # a [3:0] $end
    $var wire  8 $ y [7:0] $end
   $upscope $end
   $scope module unnamedblk1 $end
    $var wire 32 6 i [31:0] $end
   $upscope $end
  $upscope $end
 $upscope $end
$enddefinitions $end


#0
b0000 #
b00000000 $
b00000000 %
b000000000000 &
b000100000001 '
b001000000010 (
b001100000011 )
b010000000100 *
b010100000101 +
b011000000110 ,
b011100000111 -
b100000001000 .
b100100001001 /
b101000001010 0
b101100001011 1
b110000001100 2
b110100001101 3
b111000001110 4
b111100001111 5
b00000000000000000000000000000000 6
b00000000000000000000000000010000 7
b00000000000000000000000000000100 8
b00000000000000000000000000001000 9
#10
b0001 #
b00000001 $
b00000001 %
b00000000000000000000000000000001 6
#20
b0010 #
b00000010 $
b00000010 %
b00000000000000000000000000000010 6
#30
b0011 #
b00000011 $
b00000011 %
b00000000000000000000000000000011 6
#40
b0100 #
b00000100 $
b00000100 %
b00000000000000000000000000000100 6
#50
b0101 #
b00000101 $
b00000101 %
b00000000000000000000000000000101 6
#60
b0110 #
b00000110 $
b00000110 %
b00000000000000000000000000000110 6
#70
b0111 #
b00000111 $
b00000111 %
b00000000000000000000000000000111 6
#80
b1000 #
b00001000 $
b00001000 %
b00000000000000000000000000001000 6
#90
b1001 #
b00001001 $
b00001001 %
b00000000000000000000000000001001 6
#100
b1010 #
b00001010 $
b00001010 %
b00000000000000000000000000001010 6
#110
b1011 #
b00001011 $
b00001011 %
b00000000000000000000000000001011 6
#120
b1100 #
b00001100 $
b00001100 %
b00000000000000000000000000001100 6
#130
b1101 #
b00001101 $
b00001101 %
b00000000000000000000000000001101 6
#140
b1110 #
b00001110 $
b00001110 %
b00000000000000000000000000001110 6
#150
b1111 #
b00001111 $
b00001111 %
b00000000000000000000000000001111 6
#160
b00000000000000000000000000010000 6
