DDCA/Exercises/Chapter_4/Exercise_10/mux4.sv
module mux4
    (input logic[1:0] sel,
    input logic d3, d2, d1, d0,
    output logic y);

    always_comb begin
        case(sel)
            2'b11: y = d3;
            2'b10: y = d2;
            2'b01: y = d1;
            2'b00: y = d0;
            default: y = 1'bx;
        endcase
    end
endmodule

DDCA/Exercises/Chapter_4/Exercise_10/logic_mux4.sv
module logic_mux4
    (input logic a, b, c,
    output logic y);

    logic d3, d2, d1, d0;
    logic[1:0] sel;

    mux4 mux(.sel(sel), .d3(d3), .d2(d2), .d1(d1), .d0(d0), .y(y));

    always_comb begin
        sel = {a ,c};
        d3 = ~b;
        d2 = ~b;
        d1 = b;
        d0 = ~b;
    end
endmodule

DDCA/Exercises/Chapter_4/Exercise_10/tb_logic_mux4.sv
module tb_logic_mux4();
    localparam vindx = 8;
    logic a, b, c;
    logic y, y_exp;
    logic[3:0] vector_in[0 : vindx - 1];
    logic_mux4 dut(.a(a), .b(b), .c(c), .y(y));
    initial
    begin
        $readmemb("input_logic_mux4.txt", vector_in);
        $dumpfile("waveform_logic_mux4.vcd");
        $dumpvars(0, tb_logic_mux4);
        for (integer i=0; i < vindx; i++)
        begin
            {a, b, c, y_exp} = vector_in[i]; #10;
            assert (y === y_exp) else $error("Failed at line %d : input %b output %b", (i+1), {a, b, c}, y);
        end
    end
endmodule

DDCA/Exercises/Chapter_4/Exercise_10/waveform_logic_mux4.vcd
$version Generated by VerilatedVcd $end
$timescale 1ps $end

 $scope module TOP $end
  $scope module tb_logic_mux4 $end
   $var wire  1 # a $end
   $var wire  1 $ b $end
   $var wire  1 % c $end
   $var wire  4 ' vector_in[0] [3:0] $end
   $var wire  4 ( vector_in[1] [3:0] $end
   $var wire  4 ) vector_in[2] [3:0] $end
   $var wire  4 * vector_in[3] [3:0] $end
   $var wire  4 + vector_in[4] [3:0] $end
   $var wire  4 , vector_in[5] [3:0] $end
   $var wire  4 - vector_in[6] [3:0] $end
   $var wire  4 . vector_in[7] [3:0] $end
   $var wire 32 3 vindx [31:0] $end
   $var wire  1 1 y $end
   $var wire  1 & y_exp $end
   $scope module dut $end
    $var wire  1 # a $end
    $var wire  1 $ b $end
    $var wire  1 % c $end
    $var wire  1 / d0 $end
    $var wire  1 $ d1 $end
    $var wire  1 / d2 $end
    $var wire  1 / d3 $end
    $var wire  2 2 sel [1:0] $end
    $var wire  1 1 y $end
    $scope module mux $end
     $var wire  1 / d0 $end
     $var wire  1 $ d1 $end
     $var wire  1 / d2 $end
     $var wire  1 / d3 $end
     $var wire  2 2 sel [1:0] $end
     $var wire  1 1 y $end
    $upscope $end
   $upscope $end
   $scope module unnamedblk1 $end
    $var wire 32 0 i [31:0] $end
   $upscope $end
  $upscope $end
 $upscope $end
$enddefinitions $end


#0
1#
1$
1%
0&
b1110 '
b1100 (
b1011 )
b1001 *
b0111 +
b0100 ,
b0010 -
b0001 .
0/
b00000000000000000000000000000000 0
01
b11 2
b00000000000000000000000000001000 3
#10
0%
b00000000000000000000000000000001 0
b10 2
#20
0$
1%
1&
1/
b00000000000000000000000000000010 0
11
b11 2
#30
0%
b00000000000000000000000000000011 0
b10 2
#40
0#
1$
1%
0/
b00000000000000000000000000000100 0
b01 2
#50
0%
0&
b00000000000000000000000000000101 0
01
b00 2
#60
0$
1%
1/
b00000000000000000000000000000110 0
b01 2
#70
0%
1&
b00000000000000000000000000000111 0
11
b00 2
#80
b00000000000000000000000000001000 0
