DDCA/Exercises/Chapter_4/Exercise_44/four_xor_register.sv
module four_xor_register
	(input logic a, b, c, d,
	input logic clk,
	output logic y);

	logic reg_a, reg_b, reg_c, reg_d;
	logic n1, n2, n3;

	always_ff @(posedge(clk)) begin
		{reg_a, reg_b, reg_c, reg_d} <= {a, b, c, d};
		y <= n3;
	end

	assign n1 = (reg_a ^ reg_b); 
	assign n2 = (n1 ^ reg_c);
	assign n3 = (n2 ^ reg_d);
endmodule

DDCA/Exercises/Chapter_4/Exercise_44/tb_four_xor_register.sv
module tb_four_xor_register();
	integer vindx;
    localparam top=17;
	logic a, b, c, d;
	logic clk;
	logic y, y_exp;
	logic[4:0] vector_in[0 : top-1];
	four_xor_register dut(.a(a), .b(b), .c(c), .d(d), .clk(clk), .y(y));

	initial begin
		$readmemb("input_four_xor_register.txt", vector_in);
		$dumpfile("waveform_four_xor_register.vcd");
		$dumpvars(0, tb_four_xor_register);
		vindx = 0;
	end

	always begin
		clk = 0; #10;
		clk = 1; #10;
	end

	always @(posedge clk) begin
		{a, b, c, d, y_exp} = vector_in[vindx];
	end

	always @(negedge clk) begin
		if (y !== y_exp) begin
			$display("Failed at line %d : input %b output %b", (vindx+1), {a, b, c, d}, y);
		end
		vindx++;
		if (vindx>=top) begin
			$display("Test finished");
			$finish;
		end
	end
endmodule

DDCA/Exercises/Chapter_4/Exercise_44/waveform_four_xor_register.vcd
$version Generated by VerilatedVcd $end
$timescale 1ps $end

 $scope module TOP $end
  $scope module tb_four_xor_register $end
   $var wire  1 4 a $end
   $var wire  1 5 b $end
   $var wire  1 6 c $end
   $var wire  1 B clk $end
   $var wire  1 7 d $end
   $var wire 32 C top [31:0] $end
   $var wire  5 # vector_in[0] [4:0] $end
   $var wire  5 - vector_in[10] [4:0] $end
   $var wire  5 . vector_in[11] [4:0] $end
   $var wire  5 / vector_in[12] [4:0] $end
   $var wire  5 0 vector_in[13] [4:0] $end
   $var wire  5 1 vector_in[14] [4:0] $end
   $var wire  5 2 vector_in[15] [4:0] $end
   $var wire  5 3 vector_in[16] [4:0] $end
   $var wire  5 $ vector_in[1] [4:0] $end
   $var wire  5 % vector_in[2] [4:0] $end
   $var wire  5 & vector_in[3] [4:0] $end
   $var wire  5 ' vector_in[4] [4:0] $end
   $var wire  5 ( vector_in[5] [4:0] $end
   $var wire  5 ) vector_in[6] [4:0] $end
   $var wire  5 * vector_in[7] [4:0] $end
   $var wire  5 + vector_in[8] [4:0] $end
   $var wire  5 , vector_in[9] [4:0] $end
   $var wire 32 A vindx [31:0] $end
   $var wire  1 8 y $end
   $var wire  1 9 y_exp $end
   $scope module dut $end
    $var wire  1 4 a $end
    $var wire  1 5 b $end
    $var wire  1 6 c $end
    $var wire  1 B clk $end
    $var wire  1 7 d $end
    $var wire  1 > n1 $end
    $var wire  1 ? n2 $end
    $var wire  1 @ n3 $end
    $var wire  1 : reg_a $end
    $var wire  1 ; reg_b $end
    $var wire  1 < reg_c $end
    $var wire  1 = reg_d $end
    $var wire  1 8 y $end
   $upscope $end
  $upscope $end
 $upscope $end
$enddefinitions $end


#0
b00000 #
b00010 $
b00101 %
b00111 &
b01000 '
b01011 (
b01100 )
b01110 *
b10001 +
b10011 ,
b10100 -
b10110 .
b11001 /
b11010 0
b11101 1
b11111 2
b00000 3
04
05
06
07
08
09
0:
0;
0<
0=
0>
0?
0@
b00000000000000000000000000000000 A
0B
b00000000000000000000000000010001 C
#10
1B
#20
b00000000000000000000000000000001 A
0B
#30
17
1=
1@
1B
#40
b00000000000000000000000000000010 A
0B
#50
16
07
18
19
1<
0=
1?
1B
#60
b00000000000000000000000000000011 A
0B
#70
17
1=
0@
1B
#80
b00000000000000000000000000000100 A
0B
#90
15
06
07
08
09
1;
0<
0=
1>
1@
1B
#100
b00000000000000000000000000000101 A
0B
#110
17
18
19
1=
0@
1B
#120
b00000000000000000000000000000110 A
0B
#130
16
07
08
09
1<
0=
0?
1B
#140
b00000000000000000000000000000111 A
0B
#150
17
1=
1@
1B
#160
b00000000000000000000000000001000 A
0B
#170
14
05
06
07
18
19
1:
0;
0<
0=
1?
1B
#180
b00000000000000000000000000001001 A
0B
#190
17
1=
0@
1B
#200
b00000000000000000000000000001010 A
0B
#210
16
07
08
09
1<
0=
0?
1B
#220
b00000000000000000000000000001011 A
0B
#230
17
1=
1@
1B
#240
b00000000000000000000000000001100 A
0B
#250
15
06
07
18
19
1;
0<
0=
0>
0@
1B
#260
b00000000000000000000000000001101 A
0B
#270
17
08
09
1=
1@
1B
#280
b00000000000000000000000000001110 A
0B
#290
16
07
18
19
1<
0=
1?
1B
#300
b00000000000000000000000000001111 A
0B
#310
17
1=
0@
1B
#320
b00000000000000000000000000010000 A
0B
#330
04
05
06
07
08
09
0:
0;
0<
0=
0?
1B
#340
b00000000000000000000000000010001 A
0B
