DDCA/Exercises/Chapter_4/Exercise_05/minority.sv
module minority 
    (input logic a, b, c,
    output logic y);

    always_comb begin
        if ((~a & ~b) | (~b & ~c) | (~c & ~a))
            y = 1'b1;
        else
            y = 1'b0;
    end
endmodule

DDCA/Exercises/Chapter_4/Exercise_05/tb_minority.sv
module tb_minority();
    localparam vindx = 8;
    logic a, b, c;
    logic y, y_exp;
    logic[3:0] vector_in[0 : vindx - 1];
    minority dut(.a(a), .b(b), .c(c), .y(y));
    initial
    begin
        $readmemb("input_minority.txt", vector_in);
        $dumpfile("waveform_minority.vcd");
        $dumpvars(0, tb_minority);
        for (integer i=0; i < vindx; i++)
        begin
            {a, b, c, y_exp} = vector_in[i]; #10;
            assert (y === y_exp) else $error("Failed at line %d: input %b output %b", (i+1), {a,b,c}, y);
        end
    end
endmodule

DDCA/Exercises/Chapter_4/Exercise_05/waveform_minority.vcd
$version Generated by VerilatedVcd $end
$timescale 1ps $end

 $scope module TOP $end
  $scope module tb_minority $end
   $var wire  1 # a $end
   $var wire  1 $ b $end
   $var wire  1 % c $end
   $var wire  4 ( vector_in[0] [3:0] $end
   $var wire  4 ) vector_in[1] [3:0] $end
   $var wire  4 * vector_in[2] [3:0] $end
   $var wire  4 + vector_in[3] [3:0] $end
   $var wire  4 , vector_in[4] [3:0] $end
   $var wire  4 - vector_in[5] [3:0] $end
   $var wire  4 . vector_in[6] [3:0] $end
   $var wire  4 / vector_in[7] [3:0] $end
   $var wire 32 1 vindx [31:0] $end
   $var wire  1 & y $end
   $var wire  1 ' y_exp $end
   $scope module dut $end
    $var wire  1 # a $end
    $var wire  1 $ b $end
    $var wire  1 % c $end
    $var wire  1 & y $end
   $upscope $end
   $scope module unnamedblk1 $end
    $var wire 32 0 i [31:0] $end
   $upscope $end
  $upscope $end
 $upscope $end
$enddefinitions $end


#0
0#
0$
0%
1&
1'
b0001 (
b0011 )
b0101 *
b0110 +
b1001 ,
b1010 -
b1100 .
b1110 /
b00000000000000000000000000000000 0
b00000000000000000000000000001000 1
#10
1%
b00000000000000000000000000000001 0
#20
1$
0%
b00000000000000000000000000000010 0
#30
1%
0&
0'
b00000000000000000000000000000011 0
#40
1#
0$
0%
1&
1'
b00000000000000000000000000000100 0
#50
1%
0&
0'
b00000000000000000000000000000101 0
#60
1$
0%
b00000000000000000000000000000110 0
#70
1%
b00000000000000000000000000000111 0
#80
b00000000000000000000000000001000 0
